{
    "10": 41,
    "11": 78,
    "12": 229,
    "13": 215,
    "14": 231,
    "15": 236,
    "16": 154,
    "17": 230,
    "18": 54,
    "19": 39,
    "2": 38,
    "20": 195,
    "21": 208,
    "22": 205,
    "23": 116,
    "24": 26,
    "25": 3,
    "26": 85,
    "27": 37,
    "28": 235,
    "29": 149,
    "3": 11,
    "30": 61,
    "31": 58,
    "32": 65,
    "33": 57,
    "34": 100,
    "35": 212,
    "36": 258,
    "37": 121,
    "38": 197,
    "39": 163,
    "4": 183,
    "40": 161,
    "41": 5,
    "42": 35,
    "43": 29,
    "44": 74,
    "45": 187,
    "46": 94,
    "47": 182,
    "48": 158,
    "49": 24,
    "5": 186,
    "50": 209,
    "51": 108,
    "52": 18,
    "53": 189,
    "54": 67,
    "55": 79,
    "56": 137,
    "57": 251,
    "58": 28,
    "59": 55,
    "6": 253,
    "60": 31,
    "61": 22,
    "62": 15,
    "63": 204,
    "64": 135,
    "65": 145,
    "66": 130,
    "67": 25,
    "68": 109,
    "69": 228,
    "7": 250,
    "70": 86,
    "71": 90,
    "72": 244,
    "73": 147,
    "74": 132,
    "75": 119,
    "76": 255,
    "77": 240,
    "78": 201,
    "79": 222,
    "8": 178,
    "80": 263,
    "81": 248,
    "9": 30
}