{
    "10": 213,
    "100": 209,
    "101": 195,
    "102": 212,
    "103": 95,
    "104": 94,
    "105": 224,
    "106": 96,
    "107": 140,
    "108": 177,
    "109": 137,
    "11": 183,
    "110": 154,
    "111": 141,
    "112": 130,
    "113": 174,
    "114": 144,
    "115": 124,
    "116": 150,
    "117": 8,
    "118": 70,
    "119": 228,
    "12": 241,
    "120": 205,
    "121": 149,
    "122": 120,
    "123": 147,
    "124": 251,
    "125": 237,
    "126": 247,
    "127": 256,
    "128": 123,
    "129": 125,
    "13": 243,
    "130": 153,
    "131": 235,
    "132": 246,
    "133": 164,
    "134": 113,
    "135": 10,
    "136": 67,
    "137": 3,
    "138": 23,
    "14": 98,
    "15": 91,
    "16": 190,
    "17": 46,
    "18": 19,
    "19": 192,
    "2": 57,
    "20": 229,
    "21": 234,
    "22": 253,
    "23": 160,
    "24": 169,
    "25": 118,
    "26": 204,
    "27": 200,
    "28": 175,
    "29": 108,
    "3": 9,
    "30": 134,
    "31": 145,
    "32": 55,
    "33": 226,
    "34": 189,
    "35": 193,
    "36": 99,
    "37": 208,
    "38": 133,
    "39": 233,
    "4": 4,
    "40": 165,
    "41": 263,
    "42": 231,
    "43": 232,
    "44": 121,
    "45": 163,
    "46": 161,
    "47": 158,
    "48": 178,
    "49": 249,
    "5": 7,
    "50": 172,
    "51": 170,
    "52": 48,
    "53": 16,
    "54": 181,
    "55": 17,
    "56": 30,
    "57": 43,
    "58": 61,
    "59": 66,
    "6": 187,
    "60": 13,
    "61": 184,
    "62": 90,
    "63": 225,
    "64": 71,
    "65": 259,
    "66": 217,
    "67": 202,
    "68": 93,
    "69": 274,
    "7": 11,
    "70": 87,
    "71": 191,
    "72": 182,
    "73": 260,
    "74": 116,
    "75": 131,
    "76": 136,
    "77": 135,
    "78": 157,
    "79": 14,
    "8": 53,
    "80": 27,
    "81": 240,
    "82": 218,
    "83": 159,
    "84": 119,
    "85": 180,
    "86": 56,
    "87": 36,
    "88": 32,
    "89": 31,
    "9": 6,
    "90": 24,
    "91": 47,
    "92": 21,
    "93": 65,
    "94": 211,
    "95": 68,
    "96": 258,
    "97": 220,
    "98": 261,
    "99": 80
}