[
    {
        "OBP_res": 1125.95,
        "OBP_time": 0.04548192,
        "QAP_res": 2280.685,
        "QAP_time": 0.02256608,
        "id": 15
    },
    {
        "OBP_res": 1199.594,
        "OBP_time": 0.03997254,
        "QAP_res": 2284.458,
        "QAP_time": 0.00068307,
        "id": 14
    },
    {
        "OBP_res": 1140.985,
        "OBP_time": 0.03714299,
        "QAP_res": 2297.575,
        "QAP_time": 0.00061727,
        "id": 9
    },
    {
        "OBP_res": 1142.751,
        "OBP_time": 0.04395413,
        "QAP_res": 2301.829,
        "QAP_time": 0.00057888,
        "id": 1
    },
    {
        "OBP_res": 1186.86,
        "OBP_time": 0.05053186,
        "QAP_res": 2319.419,
        "QAP_time": 0.0005765,
        "id": 2
    },
    {
        "OBP_res": 1131.829,
        "OBP_time": 0.04358792,
        "QAP_res": 2330.4,
        "QAP_time": 0.00061083,
        "id": 10
    },
    {
        "OBP_res": 1119.279,
        "OBP_time": 0.04151011,
        "QAP_res": 2330.833,
        "QAP_time": 0.00057387,
        "id": 16
    },
    {
        "OBP_res": 1217.75,
        "OBP_time": 0.04176879,
        "QAP_res": 2348.052,
        "QAP_time": 0.0005722,
        "id": 13
    },
    {
        "OBP_res": 1142.691,
        "OBP_time": 0.0426259,
        "QAP_res": 2371.396,
        "QAP_time": 0.00057149,
        "id": 7
    },
    {
        "OBP_res": 1183.996,
        "OBP_time": 0.04130888,
        "QAP_res": 2373.107,
        "QAP_time": 0.0005722,
        "id": 17
    },
    {
        "OBP_res": 1229.75,
        "OBP_time": 0.04272008,
        "QAP_res": 2385.786,
        "QAP_time": 0.00060463,
        "id": 12
    },
    {
        "OBP_res": 1154.429,
        "OBP_time": 0.04429603,
        "QAP_res": 2396.529,
        "QAP_time": 0.0005796,
        "id": 8
    },
    {
        "OBP_res": 1213.109,
        "OBP_time": 0.03653407,
        "QAP_res": 2404.208,
        "QAP_time": 0.00057793,
        "id": 3
    },
    {
        "OBP_res": 1177.398,
        "OBP_time": 0.03792953,
        "QAP_res": 2407.919,
        "QAP_time": 0.00056648,
        "id": 11
    },
    {
        "OBP_res": 1142.876,
        "OBP_time": 0.04435539,
        "QAP_res": 2415.376,
        "QAP_time": 0.00061011,
        "id": 18
    },
    {
        "OBP_res": 1184.571,
        "OBP_time": 0.04558039,
        "QAP_res": 2422.88,
        "QAP_time": 0.00058055,
        "id": 4
    },
    {
        "OBP_res": 1125.39,
        "OBP_time": 0.04083586,
        "QAP_res": 2431.376,
        "QAP_time": 0.00057316,
        "id": 19
    },
    {
        "OBP_res": 1237.332,
        "OBP_time": 0.05048299,
        "QAP_res": 2446.56,
        "QAP_time": 0.00055194,
        "id": 0
    },
    {
        "OBP_res": 1096.102,
        "OBP_time": 0.04258084,
        "QAP_res": 2477.161,
        "QAP_time": 0.00055432,
        "id": 6
    },
    {
        "OBP_res": 1174.25,
        "OBP_time": 0.03845644,
        "QAP_res": 2486.685,
        "QAP_time": 0.00059056,
        "id": 5
    }
]