[
    {
        "OBP_res": 7643.586,
        "OBP_time": 3.00258517,
        "QAP_res": 12946.497,
        "QAP_time": 0.02275825,
        "id": 18
    },
    {
        "OBP_res": 7603.139,
        "OBP_time": 3.07655811,
        "QAP_res": 13033.382,
        "QAP_time": 0.02245593,
        "id": 12
    },
    {
        "OBP_res": 7645.547,
        "OBP_time": 2.96929598,
        "QAP_res": 13107.057,
        "QAP_time": 0.02349639,
        "id": 19
    },
    {
        "OBP_res": 7440.262,
        "OBP_time": 3.0748198,
        "QAP_res": 13107.825,
        "QAP_time": 0.02223563,
        "id": 8
    },
    {
        "OBP_res": 7694.309,
        "OBP_time": 3.04436612,
        "QAP_res": 13121.413,
        "QAP_time": 0.02347636,
        "id": 9
    },
    {
        "OBP_res": 7614.842,
        "OBP_time": 3.1453917,
        "QAP_res": 13123.457,
        "QAP_time": 0.02194452,
        "id": 10
    },
    {
        "OBP_res": 7731.41,
        "OBP_time": 3.239254,
        "QAP_res": 13167.285,
        "QAP_time": 0.02286625,
        "id": 14
    },
    {
        "OBP_res": 7566.818,
        "OBP_time": 2.88671017,
        "QAP_res": 13169.08,
        "QAP_time": 0.02334476,
        "id": 17
    },
    {
        "OBP_res": 7722.225,
        "OBP_time": 3.30004144,
        "QAP_res": 13173.245,
        "QAP_time": 0.02208877,
        "id": 6
    },
    {
        "OBP_res": 7718.072,
        "OBP_time": 3.23409057,
        "QAP_res": 13194.797,
        "QAP_time": 0.02276635,
        "id": 13
    },
    {
        "OBP_res": 7681.523,
        "OBP_time": 3.50989461,
        "QAP_res": 13213.909,
        "QAP_time": 0.02232051,
        "id": 11
    },
    {
        "OBP_res": 7668.102,
        "OBP_time": 3.00319123,
        "QAP_res": 13230.937,
        "QAP_time": 0.02343154,
        "id": 1
    },
    {
        "OBP_res": 7736.701,
        "OBP_time": 3.15485144,
        "QAP_res": 13255.245,
        "QAP_time": 0.02215767,
        "id": 4
    },
    {
        "OBP_res": 7657.521,
        "OBP_time": 3.23551083,
        "QAP_res": 13271.309,
        "QAP_time": 0.02318811,
        "id": 15
    },
    {
        "OBP_res": 7673.668,
        "OBP_time": 2.94317603,
        "QAP_res": 13302.435,
        "QAP_time": 0.02258968,
        "id": 0
    },
    {
        "OBP_res": 7875.725,
        "OBP_time": 3.11341715,
        "QAP_res": 13316.669,
        "QAP_time": 0.02361393,
        "id": 3
    },
    {
        "OBP_res": 7699.84,
        "OBP_time": 3.06780577,
        "QAP_res": 13424.096,
        "QAP_time": 0.02260852,
        "id": 5
    },
    {
        "OBP_res": 7703.191,
        "OBP_time": 4.02252197,
        "QAP_res": 13533.992,
        "QAP_time": 0.02247858,
        "id": 16
    },
    {
        "OBP_res": 7700.193,
        "OBP_time": 3.10067296,
        "QAP_res": 13559.259,
        "QAP_time": 0.02190566,
        "id": 2
    },
    {
        "OBP_res": 7702.604,
        "OBP_time": 3.17155766,
        "QAP_res": 13561.952,
        "QAP_time": 0.02219534,
        "id": 7
    }
]