{
    "ASSIGNMENT_OPTIONS": {
        "assignmentType": "firstAssignment",
        "evaluationData": "pickingLog",
        "openLocations": "allExceptPickingLog"
    },
    "CAPACITIES": 24,
    "DATA_SECTION": "",
    "HEADER": {
        "COMMENTS": {
            "Best known objective": "4453.838",
            "Computational time (s)": "27.791456937789917",
            "descr": "Modified TSPLIB for the SLAP"
        },
        "VERSION": "SLAP 1.0"
    },
    "NAME": "c795_afb3",
    "NUM_CAPACITIES": 1,
    "NUM_VEHICLES": 17,
    "NUM_VISITS": 795,
    "ORDERS": {
        "1": [
            "2"
        ],
        "10": [
            "17",
            "18",
            "19"
        ],
        "100": [
            "202",
            "203"
        ],
        "101": [
            "204"
        ],
        "102": [
            "205",
            "206"
        ],
        "103": [
            "207",
            "208"
        ],
        "104": [
            "209",
            "210",
            "211"
        ],
        "105": [
            "212",
            "213",
            "214"
        ],
        "106": [
            "215"
        ],
        "107": [
            "216"
        ],
        "108": [
            "217"
        ],
        "109": [
            "218"
        ],
        "11": [
            "20",
            "21"
        ],
        "110": [
            "219",
            "220"
        ],
        "111": [
            "221",
            "222"
        ],
        "112": [
            "223",
            "224",
            "225"
        ],
        "113": [
            "226",
            "227"
        ],
        "114": [
            "228"
        ],
        "115": [
            "229",
            "230"
        ],
        "116": [
            "231"
        ],
        "117": [
            "232",
            "233",
            "234"
        ],
        "118": [
            "235",
            "236"
        ],
        "119": [
            "237",
            "238"
        ],
        "12": [
            "22",
            "23",
            "24"
        ],
        "120": [
            "239",
            "240",
            "241"
        ],
        "121": [
            "242",
            "243"
        ],
        "122": [
            "244",
            "245"
        ],
        "123": [
            "246"
        ],
        "124": [
            "247",
            "248"
        ],
        "125": [
            "249"
        ],
        "126": [
            "250",
            "251",
            "252"
        ],
        "127": [
            "253",
            "254"
        ],
        "128": [
            "255",
            "256"
        ],
        "129": [
            "257",
            "258"
        ],
        "13": [
            "25",
            "26",
            "27"
        ],
        "130": [
            "259",
            "260"
        ],
        "131": [
            "261",
            "262",
            "263"
        ],
        "132": [
            "264",
            "265",
            "266"
        ],
        "133": [
            "267",
            "268"
        ],
        "134": [
            "269",
            "270",
            "271"
        ],
        "135": [
            "272"
        ],
        "136": [
            "273"
        ],
        "137": [
            "274"
        ],
        "138": [
            "275",
            "276",
            "277"
        ],
        "139": [
            "278",
            "279"
        ],
        "14": [
            "28"
        ],
        "140": [
            "280",
            "281"
        ],
        "141": [
            "282",
            "283"
        ],
        "142": [
            "284",
            "285"
        ],
        "143": [
            "286"
        ],
        "144": [
            "287",
            "288",
            "289"
        ],
        "145": [
            "290",
            "291",
            "292"
        ],
        "146": [
            "293",
            "294"
        ],
        "147": [
            "295",
            "296"
        ],
        "148": [
            "297",
            "298",
            "299"
        ],
        "149": [
            "300",
            "584"
        ],
        "15": [
            "29"
        ],
        "150": [
            "301",
            "302",
            "194"
        ],
        "151": [
            "303",
            "304"
        ],
        "152": [
            "305",
            "306",
            "307"
        ],
        "153": [
            "308",
            "309"
        ],
        "154": [
            "310",
            "311"
        ],
        "155": [
            "312"
        ],
        "156": [
            "313"
        ],
        "157": [
            "314"
        ],
        "158": [
            "315",
            "316",
            "317"
        ],
        "159": [
            "318",
            "319",
            "320"
        ],
        "16": [
            "30",
            "31",
            "32"
        ],
        "160": [
            "321",
            "322",
            "323"
        ],
        "161": [
            "324"
        ],
        "162": [
            "325",
            "326",
            "327"
        ],
        "163": [
            "328"
        ],
        "164": [
            "329"
        ],
        "165": [
            "330",
            "331",
            "332"
        ],
        "166": [
            "333"
        ],
        "167": [
            "334",
            "335"
        ],
        "168": [
            "336",
            "337"
        ],
        "169": [
            "338",
            "339"
        ],
        "17": [
            "33",
            "34"
        ],
        "170": [
            "340"
        ],
        "171": [
            "341"
        ],
        "172": [
            "342",
            "343",
            "344"
        ],
        "173": [
            "345",
            "346"
        ],
        "174": [
            "347",
            "348",
            "349"
        ],
        "175": [
            "350",
            "351",
            "352"
        ],
        "176": [
            "353"
        ],
        "177": [
            "354",
            "355",
            "356"
        ],
        "178": [
            "357"
        ],
        "179": [
            "358",
            "359"
        ],
        "18": [
            "35"
        ],
        "180": [
            "360",
            "361"
        ],
        "181": [
            "362"
        ],
        "182": [
            "363",
            "364",
            "365"
        ],
        "183": [
            "366",
            "367",
            "368"
        ],
        "184": [
            "369"
        ],
        "185": [
            "370",
            "371",
            "372"
        ],
        "186": [
            "373"
        ],
        "187": [
            "374"
        ],
        "188": [
            "375",
            "376",
            "377"
        ],
        "189": [
            "378",
            "379"
        ],
        "19": [
            "36",
            "37"
        ],
        "190": [
            "380",
            "381",
            "382"
        ],
        "191": [
            "383",
            "384",
            "385"
        ],
        "192": [
            "386"
        ],
        "193": [
            "387",
            "388"
        ],
        "194": [
            "389"
        ],
        "195": [
            "390",
            "391",
            "392"
        ],
        "196": [
            "393",
            "394"
        ],
        "197": [
            "395",
            "396",
            "777"
        ],
        "198": [
            "397"
        ],
        "199": [
            "398"
        ],
        "2": [
            "3",
            "4",
            "5"
        ],
        "20": [
            "38",
            "39",
            "40"
        ],
        "200": [
            "399"
        ],
        "201": [
            "400"
        ],
        "202": [
            "401",
            "402"
        ],
        "203": [
            "403"
        ],
        "204": [
            "404",
            "405",
            "406"
        ],
        "205": [
            "407"
        ],
        "206": [
            "408",
            "409",
            "410"
        ],
        "207": [
            "411",
            "412",
            "413"
        ],
        "208": [
            "414"
        ],
        "209": [
            "415",
            "416",
            "417"
        ],
        "21": [
            "41",
            "42",
            "43"
        ],
        "210": [
            "418"
        ],
        "211": [
            "419"
        ],
        "212": [
            "420",
            "421"
        ],
        "213": [
            "422",
            "423",
            "424"
        ],
        "214": [
            "425",
            "426",
            "427"
        ],
        "215": [
            "428",
            "429",
            "430"
        ],
        "216": [
            "431",
            "432"
        ],
        "217": [
            "433",
            "434",
            "435"
        ],
        "218": [
            "436"
        ],
        "219": [
            "437",
            "438"
        ],
        "22": [
            "44",
            "45",
            "46"
        ],
        "220": [
            "439",
            "440"
        ],
        "221": [
            "441",
            "442",
            "443"
        ],
        "222": [
            "444",
            "445",
            "446"
        ],
        "223": [
            "447",
            "448"
        ],
        "224": [
            "449",
            "450"
        ],
        "225": [
            "451",
            "452"
        ],
        "226": [
            "453",
            "454"
        ],
        "227": [
            "455",
            "456",
            "457"
        ],
        "228": [
            "458"
        ],
        "229": [
            "459",
            "460",
            "461"
        ],
        "23": [
            "47",
            "48",
            "49"
        ],
        "230": [
            "462"
        ],
        "231": [
            "463",
            "444"
        ],
        "232": [
            "464",
            "465",
            "466"
        ],
        "233": [
            "467",
            "468",
            "469"
        ],
        "234": [
            "470",
            "471",
            "472"
        ],
        "235": [
            "473",
            "474",
            "475"
        ],
        "236": [
            "476",
            "477"
        ],
        "237": [
            "478"
        ],
        "238": [
            "479",
            "480",
            "481",
            "765"
        ],
        "239": [
            "482",
            "483"
        ],
        "24": [
            "50",
            "51"
        ],
        "240": [
            "484",
            "485",
            "486"
        ],
        "241": [
            "487",
            "488"
        ],
        "242": [
            "489",
            "490"
        ],
        "243": [
            "491",
            "492"
        ],
        "244": [
            "493"
        ],
        "245": [
            "494"
        ],
        "246": [
            "495",
            "496",
            "497"
        ],
        "247": [
            "498",
            "499",
            "500"
        ],
        "248": [
            "501",
            "502"
        ],
        "249": [
            "503"
        ],
        "25": [
            "52",
            "53",
            "54"
        ],
        "250": [
            "504"
        ],
        "251": [
            "505",
            "506",
            "507"
        ],
        "252": [
            "508",
            "509"
        ],
        "253": [
            "510",
            "511"
        ],
        "254": [
            "512",
            "513",
            "514"
        ],
        "255": [
            "515"
        ],
        "256": [
            "516",
            "517",
            "518"
        ],
        "257": [
            "519"
        ],
        "258": [
            "520",
            "521",
            "522"
        ],
        "259": [
            "523",
            "524",
            "525"
        ],
        "26": [
            "55",
            "513"
        ],
        "260": [
            "526",
            "527"
        ],
        "261": [
            "528"
        ],
        "262": [
            "529"
        ],
        "263": [
            "530",
            "531"
        ],
        "264": [
            "532",
            "533",
            "534"
        ],
        "265": [
            "535",
            "536",
            "537"
        ],
        "266": [
            "538"
        ],
        "267": [
            "539"
        ],
        "268": [
            "540"
        ],
        "269": [
            "541",
            "542",
            "543"
        ],
        "27": [
            "56",
            "57"
        ],
        "270": [
            "544"
        ],
        "271": [
            "545",
            "546",
            "547"
        ],
        "272": [
            "548",
            "549"
        ],
        "273": [
            "550"
        ],
        "274": [
            "551",
            "552",
            "553"
        ],
        "275": [
            "554",
            "555"
        ],
        "276": [
            "556"
        ],
        "277": [
            "557",
            "558",
            "559"
        ],
        "278": [
            "560"
        ],
        "279": [
            "561",
            "562"
        ],
        "28": [
            "58",
            "59",
            "60",
            "702"
        ],
        "280": [
            "563",
            "564"
        ],
        "281": [
            "565"
        ],
        "282": [
            "566",
            "567",
            "568"
        ],
        "283": [
            "569"
        ],
        "284": [
            "570"
        ],
        "285": [
            "571"
        ],
        "286": [
            "572",
            "573",
            "574"
        ],
        "287": [
            "575",
            "576",
            "577"
        ],
        "288": [
            "578",
            "579",
            "339"
        ],
        "289": [
            "580",
            "581",
            "582"
        ],
        "29": [
            "61"
        ],
        "290": [
            "583",
            "584"
        ],
        "291": [
            "585",
            "586",
            "587"
        ],
        "292": [
            "588",
            "589",
            "590"
        ],
        "293": [
            "591"
        ],
        "294": [
            "592",
            "593"
        ],
        "295": [
            "594"
        ],
        "296": [
            "595",
            "596",
            "597"
        ],
        "297": [
            "598",
            "599"
        ],
        "298": [
            "600"
        ],
        "299": [
            "601",
            "602",
            "603"
        ],
        "3": [
            "6",
            "7"
        ],
        "30": [
            "62"
        ],
        "300": [
            "604"
        ],
        "301": [
            "605",
            "606",
            "607"
        ],
        "302": [
            "608",
            "609",
            "610"
        ],
        "303": [
            "611",
            "612",
            "304"
        ],
        "304": [
            "613",
            "614",
            "615"
        ],
        "305": [
            "616"
        ],
        "306": [
            "617",
            "618",
            "619"
        ],
        "307": [
            "620"
        ],
        "308": [
            "621",
            "622",
            "623"
        ],
        "309": [
            "624"
        ],
        "31": [
            "63"
        ],
        "310": [
            "625",
            "626",
            "627"
        ],
        "311": [
            "628",
            "629"
        ],
        "312": [
            "630",
            "631"
        ],
        "313": [
            "632",
            "633",
            "634"
        ],
        "314": [
            "635"
        ],
        "315": [
            "636",
            "637",
            "638"
        ],
        "316": [
            "639"
        ],
        "317": [
            "640"
        ],
        "318": [
            "641"
        ],
        "319": [
            "642",
            "643",
            "644"
        ],
        "32": [
            "64",
            "65",
            "66"
        ],
        "320": [
            "645",
            "646"
        ],
        "321": [
            "647",
            "648",
            "649"
        ],
        "322": [
            "650",
            "651",
            "652"
        ],
        "323": [
            "653"
        ],
        "324": [
            "654"
        ],
        "325": [
            "655",
            "656"
        ],
        "326": [
            "657",
            "658",
            "659"
        ],
        "327": [
            "660",
            "661",
            "662"
        ],
        "328": [
            "663",
            "664",
            "665"
        ],
        "329": [
            "666"
        ],
        "33": [
            "67",
            "68",
            "69"
        ],
        "330": [
            "667",
            "668"
        ],
        "331": [
            "669",
            "670",
            "671"
        ],
        "332": [
            "672",
            "673",
            "674"
        ],
        "333": [
            "675",
            "676",
            "677"
        ],
        "334": [
            "678"
        ],
        "335": [
            "679",
            "680"
        ],
        "336": [
            "681"
        ],
        "337": [
            "682",
            "683"
        ],
        "338": [
            "684",
            "685",
            "686"
        ],
        "339": [
            "687",
            "688",
            "689"
        ],
        "34": [
            "70",
            "71"
        ],
        "340": [
            "690",
            "691",
            "692"
        ],
        "341": [
            "693"
        ],
        "342": [
            "694",
            "695"
        ],
        "343": [
            "696"
        ],
        "344": [
            "697",
            "698"
        ],
        "345": [
            "699",
            "700",
            "701"
        ],
        "346": [
            "702"
        ],
        "347": [
            "703",
            "704",
            "705"
        ],
        "348": [
            "706",
            "707"
        ],
        "349": [
            "708",
            "709",
            "710"
        ],
        "35": [
            "72"
        ],
        "350": [
            "711"
        ],
        "351": [
            "712",
            "713"
        ],
        "352": [
            "714"
        ],
        "353": [
            "715",
            "716"
        ],
        "354": [
            "717"
        ],
        "355": [
            "718",
            "719"
        ],
        "356": [
            "720"
        ],
        "357": [
            "721",
            "722"
        ],
        "358": [
            "723",
            "387"
        ],
        "359": [
            "724"
        ],
        "36": [
            "73",
            "74"
        ],
        "360": [
            "725",
            "726",
            "727"
        ],
        "361": [
            "728",
            "729"
        ],
        "362": [
            "730",
            "731",
            "732"
        ],
        "363": [
            "733",
            "734"
        ],
        "364": [
            "735"
        ],
        "365": [
            "736",
            "737"
        ],
        "366": [
            "738"
        ],
        "367": [
            "739"
        ],
        "368": [
            "740",
            "741",
            "742"
        ],
        "369": [
            "743",
            "744"
        ],
        "37": [
            "75"
        ],
        "370": [
            "745"
        ],
        "371": [
            "746"
        ],
        "372": [
            "747",
            "748",
            "749"
        ],
        "373": [
            "750",
            "751",
            "752"
        ],
        "374": [
            "753",
            "754",
            "755"
        ],
        "375": [
            "756"
        ],
        "376": [
            "757"
        ],
        "377": [
            "758"
        ],
        "378": [
            "759",
            "760",
            "761"
        ],
        "379": [
            "762",
            "763"
        ],
        "38": [
            "76",
            "77",
            "78"
        ],
        "380": [
            "764"
        ],
        "381": [
            "765"
        ],
        "382": [
            "766"
        ],
        "383": [
            "767",
            "768"
        ],
        "384": [
            "769",
            "770",
            "771"
        ],
        "385": [
            "772",
            "173"
        ],
        "386": [
            "773",
            "774"
        ],
        "387": [
            "775",
            "776"
        ],
        "388": [
            "777"
        ],
        "389": [
            "778",
            "779",
            "780"
        ],
        "39": [
            "79"
        ],
        "4": [
            "8"
        ],
        "40": [
            "80"
        ],
        "41": [
            "81",
            "82",
            "83"
        ],
        "42": [
            "84",
            "85"
        ],
        "43": [
            "86",
            "87"
        ],
        "44": [
            "88",
            "89"
        ],
        "45": [
            "90",
            "91"
        ],
        "46": [
            "92",
            "93",
            "446"
        ],
        "47": [
            "94"
        ],
        "48": [
            "95",
            "472"
        ],
        "49": [
            "96",
            "97",
            "98"
        ],
        "5": [
            "9",
            "10"
        ],
        "50": [
            "99",
            "100"
        ],
        "51": [
            "101",
            "102",
            "103"
        ],
        "52": [
            "104",
            "105",
            "106"
        ],
        "53": [
            "107"
        ],
        "54": [
            "108"
        ],
        "55": [
            "109"
        ],
        "56": [
            "110",
            "111"
        ],
        "57": [
            "112",
            "113",
            "114"
        ],
        "58": [
            "115",
            "116"
        ],
        "59": [
            "117"
        ],
        "6": [
            "11"
        ],
        "60": [
            "118",
            "119"
        ],
        "61": [
            "120",
            "121",
            "122"
        ],
        "62": [
            "123",
            "124",
            "167"
        ],
        "63": [
            "125",
            "126",
            "127"
        ],
        "64": [
            "128",
            "129",
            "130"
        ],
        "65": [
            "131",
            "132",
            "133"
        ],
        "66": [
            "134",
            "135",
            "136"
        ],
        "67": [
            "137"
        ],
        "68": [
            "138",
            "139"
        ],
        "69": [
            "140",
            "141",
            "142"
        ],
        "7": [
            "12",
            "13"
        ],
        "70": [
            "143",
            "30"
        ],
        "71": [
            "144"
        ],
        "72": [
            "145",
            "146",
            "147"
        ],
        "73": [
            "148",
            "149",
            "150"
        ],
        "74": [
            "151",
            "152",
            "153"
        ],
        "75": [
            "154",
            "155",
            "156"
        ],
        "76": [
            "157"
        ],
        "77": [
            "158",
            "159",
            "160"
        ],
        "78": [
            "161",
            "162",
            "163"
        ],
        "79": [
            "164",
            "165"
        ],
        "8": [
            "14"
        ],
        "80": [
            "166",
            "167"
        ],
        "81": [
            "168",
            "169"
        ],
        "82": [
            "170",
            "171",
            "172"
        ],
        "83": [
            "173"
        ],
        "84": [
            "174"
        ],
        "85": [
            "175"
        ],
        "86": [
            "176",
            "177",
            "178"
        ],
        "87": [
            "179",
            "180",
            "181"
        ],
        "88": [
            "182"
        ],
        "89": [
            "183"
        ],
        "9": [
            "15",
            "16"
        ],
        "90": [
            "184",
            "185"
        ],
        "91": [
            "186"
        ],
        "92": [
            "187",
            "188",
            "189"
        ],
        "93": [
            "190",
            "191",
            "192"
        ],
        "94": [
            "193"
        ],
        "95": [
            "194"
        ],
        "96": [
            "195",
            "196"
        ],
        "97": [
            "197"
        ],
        "98": [
            "198",
            "199"
        ],
        "99": [
            "200",
            "201",
            "489"
        ]
    },
    "SKUS_TO_SLOT": [
        "209",
        "211",
        "246",
        "258",
        "25",
        "264",
        "268",
        "275",
        "296",
        "300",
        "584",
        "303",
        "305",
        "317",
        "331",
        "335",
        "345",
        "366",
        "374",
        "380",
        "382",
        "391",
        "777",
        "397",
        "38",
        "410",
        "415",
        "42",
        "423",
        "439",
        "451",
        "457",
        "469",
        "484",
        "489",
        "490",
        "496",
        "500",
        "523",
        "534",
        "544",
        "546",
        "555",
        "601",
        "62",
        "610",
        "626",
        "647",
        "651",
        "653",
        "654",
        "658",
        "662",
        "669",
        "700",
        "704",
        "709",
        "712",
        "724",
        "73",
        "735",
        "739",
        "752",
        "761",
        "77",
        "767",
        "770",
        "773",
        "776",
        "89",
        "446",
        "95",
        "98",
        "114",
        "116",
        "11",
        "124",
        "129",
        "12",
        "158"
    ],
    "TIMESTEP": "1",
    "TIME_AVAIL_SECTION": {
        "1": "1",
        "10": "1",
        "100": "1",
        "101": "1",
        "102": "1",
        "103": "1",
        "104": "1",
        "105": "1",
        "106": "1",
        "107": "1",
        "108": "1",
        "109": "1",
        "11": "1",
        "110": "1",
        "111": "1",
        "112": "1",
        "113": "1",
        "114": "1",
        "115": "1",
        "116": "1",
        "117": "1",
        "118": "1",
        "119": "1",
        "12": "1",
        "120": "1",
        "121": "1",
        "122": "1",
        "123": "1",
        "124": "1",
        "125": "1",
        "126": "1",
        "127": "1",
        "128": "1",
        "129": "1",
        "13": "1",
        "130": "1",
        "131": "1",
        "132": "1",
        "133": "1",
        "134": "1",
        "135": "1",
        "136": "1",
        "137": "1",
        "138": "1",
        "139": "1",
        "14": "1",
        "140": "1",
        "141": "1",
        "142": "1",
        "143": "1",
        "144": "1",
        "145": "1",
        "146": "1",
        "147": "1",
        "148": "1",
        "149": "1",
        "15": "1",
        "150": "1",
        "151": "1",
        "152": "1",
        "153": "1",
        "154": "1",
        "155": "1",
        "156": "1",
        "157": "1",
        "158": "1",
        "159": "1",
        "16": "1",
        "160": "1",
        "161": "1",
        "162": "1",
        "163": "1",
        "164": "1",
        "165": "1",
        "166": "1",
        "167": "1",
        "168": "1",
        "169": "1",
        "17": "1",
        "170": "1",
        "171": "1",
        "172": "1",
        "173": "1",
        "174": "1",
        "175": "1",
        "176": "1",
        "177": "1",
        "178": "1",
        "179": "1",
        "18": "1",
        "180": "1",
        "181": "1",
        "182": "1",
        "183": "1",
        "184": "1",
        "185": "1",
        "186": "1",
        "187": "1",
        "188": "1",
        "189": "1",
        "19": "1",
        "190": "1",
        "191": "1",
        "192": "1",
        "193": "1",
        "194": "1",
        "195": "1",
        "196": "1",
        "197": "1",
        "198": "1",
        "199": "1",
        "2": "1",
        "20": "1",
        "200": "1",
        "201": "1",
        "202": "1",
        "203": "1",
        "204": "1",
        "205": "1",
        "206": "1",
        "207": "1",
        "208": "1",
        "209": "1",
        "21": "1",
        "210": "1",
        "211": "1",
        "212": "1",
        "213": "1",
        "214": "1",
        "215": "1",
        "216": "1",
        "217": "1",
        "218": "1",
        "219": "1",
        "22": "1",
        "220": "1",
        "221": "1",
        "222": "1",
        "223": "1",
        "224": "1",
        "225": "1",
        "226": "1",
        "227": "1",
        "228": "1",
        "229": "1",
        "23": "1",
        "230": "1",
        "231": "1",
        "232": "1",
        "233": "1",
        "234": "1",
        "235": "1",
        "236": "1",
        "237": "1",
        "238": "1",
        "239": "1",
        "24": "1",
        "240": "1",
        "241": "1",
        "242": "1",
        "243": "1",
        "244": "1",
        "245": "1",
        "246": "1",
        "247": "1",
        "248": "1",
        "249": "1",
        "25": "1",
        "250": "1",
        "251": "1",
        "252": "1",
        "253": "1",
        "254": "1",
        "255": "1",
        "256": "1",
        "257": "1",
        "258": "1",
        "259": "1",
        "26": "1",
        "260": "1",
        "261": "1",
        "262": "1",
        "263": "1",
        "264": "1",
        "265": "1",
        "266": "1",
        "267": "1",
        "268": "1",
        "269": "1",
        "27": "1",
        "270": "1",
        "271": "1",
        "272": "1",
        "273": "1",
        "274": "1",
        "275": "1",
        "276": "1",
        "277": "1",
        "278": "1",
        "279": "1",
        "28": "1",
        "280": "1",
        "281": "1",
        "282": "1",
        "283": "1",
        "284": "1",
        "285": "1",
        "286": "1",
        "287": "1",
        "288": "1",
        "289": "1",
        "29": "1",
        "290": "1",
        "291": "1",
        "292": "1",
        "293": "1",
        "294": "1",
        "295": "1",
        "296": "1",
        "297": "1",
        "298": "1",
        "299": "1",
        "3": "1",
        "30": "1",
        "300": "1",
        "301": "1",
        "302": "1",
        "303": "1",
        "304": "1",
        "305": "1",
        "306": "1",
        "307": "1",
        "308": "1",
        "309": "1",
        "31": "1",
        "310": "1",
        "311": "1",
        "312": "1",
        "313": "1",
        "314": "1",
        "315": "1",
        "316": "1",
        "317": "1",
        "318": "1",
        "319": "1",
        "32": "1",
        "320": "1",
        "321": "1",
        "322": "1",
        "323": "1",
        "324": "1",
        "325": "1",
        "326": "1",
        "327": "1",
        "328": "1",
        "329": "1",
        "33": "1",
        "330": "1",
        "331": "1",
        "332": "1",
        "333": "1",
        "334": "1",
        "335": "1",
        "336": "1",
        "337": "1",
        "338": "1",
        "339": "1",
        "34": "1",
        "340": "1",
        "341": "1",
        "342": "1",
        "343": "1",
        "344": "1",
        "345": "1",
        "346": "1",
        "347": "1",
        "348": "1",
        "349": "1",
        "35": "1",
        "350": "1",
        "351": "1",
        "352": "1",
        "353": "1",
        "354": "1",
        "355": "1",
        "356": "1",
        "357": "1",
        "358": "1",
        "359": "1",
        "36": "1",
        "360": "1",
        "361": "1",
        "362": "1",
        "363": "1",
        "364": "1",
        "365": "1",
        "366": "1",
        "367": "1",
        "368": "1",
        "369": "1",
        "37": "1",
        "370": "1",
        "371": "1",
        "372": "1",
        "373": "1",
        "374": "1",
        "375": "1",
        "376": "1",
        "377": "1",
        "378": "1",
        "379": "1",
        "38": "1",
        "380": "1",
        "381": "1",
        "382": "1",
        "383": "1",
        "384": "1",
        "385": "1",
        "386": "1",
        "387": "1",
        "388": "1",
        "389": "1",
        "39": "1",
        "4": "1",
        "40": "1",
        "41": "1",
        "42": "1",
        "43": "1",
        "44": "1",
        "45": "1",
        "46": "1",
        "47": "1",
        "48": "1",
        "49": "1",
        "5": "1",
        "50": "1",
        "51": "1",
        "52": "1",
        "53": "1",
        "54": "1",
        "55": "1",
        "56": "1",
        "57": "1",
        "58": "1",
        "59": "1",
        "6": "1",
        "60": "1",
        "61": "1",
        "62": "1",
        "63": "1",
        "64": "1",
        "65": "1",
        "66": "1",
        "67": "1",
        "68": "1",
        "69": "1",
        "7": "1",
        "70": "1",
        "71": "1",
        "72": "1",
        "73": "1",
        "74": "1",
        "75": "1",
        "76": "1",
        "77": "1",
        "78": "1",
        "79": "1",
        "8": "1",
        "80": "1",
        "81": "1",
        "82": "1",
        "83": "1",
        "84": "1",
        "85": "1",
        "86": "1",
        "87": "1",
        "88": "1",
        "89": "1",
        "9": "1",
        "90": "1",
        "91": "1",
        "92": "1",
        "93": "1",
        "94": "1",
        "95": "1",
        "96": "1",
        "97": "1",
        "98": "1",
        "99": "1"
    },
    "VISIT_LOCATION_SECTION": {
        "10": "2110",
        "100": "708",
        "101": "2089",
        "102": "1198",
        "103": "1695",
        "104": "725",
        "105": "1305",
        "106": "1507",
        "107": "2127",
        "108": "337",
        "109": "1142",
        "11": null,
        "110": "945",
        "111": "523",
        "112": "1439",
        "113": "59",
        "114": null,
        "115": "1140",
        "116": null,
        "117": "905",
        "118": "113",
        "119": "1962",
        "12": null,
        "120": "662",
        "121": "1642",
        "122": "1876",
        "123": "1216",
        "124": null,
        "125": "103",
        "126": "10",
        "127": "573",
        "128": "842",
        "129": null,
        "13": "1031",
        "130": "2121",
        "131": "1702",
        "132": "1201",
        "133": "67",
        "134": "316",
        "135": "246",
        "136": "1646",
        "137": "378",
        "138": "987",
        "139": "403",
        "14": "397",
        "140": "711",
        "141": "635",
        "142": "1056",
        "143": "604",
        "144": "1899",
        "145": "1986",
        "146": "282",
        "147": "1508",
        "148": "921",
        "149": "601",
        "15": "556",
        "150": "1025",
        "151": "1595",
        "152": "1632",
        "153": "371",
        "154": "19",
        "155": "1239",
        "156": "978",
        "157": "486",
        "158": null,
        "159": "701",
        "16": "1404",
        "160": "2162",
        "161": "1180",
        "162": "387",
        "163": "58",
        "164": "1894",
        "165": "1788",
        "166": "1281",
        "167": "228",
        "168": "1270",
        "169": "869",
        "17": "633",
        "170": "2144",
        "171": "1129",
        "172": "1371",
        "173": "1183",
        "174": "241",
        "175": "306",
        "176": "1544",
        "177": "1501",
        "178": "607",
        "179": "1966",
        "18": "1075",
        "180": "676",
        "181": "2170",
        "182": "766",
        "183": "393",
        "184": "1010",
        "185": "738",
        "186": "673",
        "187": "1104",
        "188": "1579",
        "189": "231",
        "19": "2013",
        "190": "20",
        "191": "658",
        "192": "225",
        "193": "974",
        "194": "2018",
        "195": "252",
        "196": "804",
        "197": "130",
        "198": "655",
        "199": "1455",
        "2": "820",
        "20": "1341",
        "200": "815",
        "201": "1037",
        "202": "356",
        "203": "1505",
        "204": "1711",
        "205": "743",
        "206": "1345",
        "207": "1602",
        "208": "866",
        "209": null,
        "21": "1136",
        "210": "1549",
        "211": null,
        "212": "1076",
        "213": "1814",
        "214": "1378",
        "215": "941",
        "216": "1210",
        "217": "1490",
        "218": "2079",
        "219": "917",
        "22": "1560",
        "220": "100",
        "221": "783",
        "222": "684",
        "223": "96",
        "224": "1127",
        "225": "1200",
        "226": "351",
        "227": "1413",
        "228": "1258",
        "229": "2034",
        "23": "1740",
        "230": "1388",
        "231": "1236",
        "232": "726",
        "233": "1757",
        "234": "495",
        "235": "872",
        "236": "1105",
        "237": "1698",
        "238": "1277",
        "239": "1250",
        "24": "682",
        "240": "975",
        "241": "1175",
        "242": "163",
        "243": "1156",
        "244": "1670",
        "245": "382",
        "246": null,
        "247": "489",
        "248": "1063",
        "249": "873",
        "25": null,
        "250": "454",
        "251": "1552",
        "252": "471",
        "253": "888",
        "254": "1532",
        "255": "1230",
        "256": "1949",
        "257": "303",
        "258": null,
        "259": "499",
        "26": "264",
        "260": "919",
        "261": "24",
        "262": "1685",
        "263": "565",
        "264": null,
        "265": "257",
        "266": "1238",
        "267": "1665",
        "268": null,
        "269": "1747",
        "27": "986",
        "270": "952",
        "271": "2060",
        "272": "1528",
        "273": "1485",
        "274": "1333",
        "275": null,
        "276": "1857",
        "277": "1947",
        "278": "2036",
        "279": "616",
        "28": "1806",
        "280": "1944",
        "281": "1763",
        "282": "729",
        "283": "1331",
        "284": "144",
        "285": "1752",
        "286": "1819",
        "287": "839",
        "288": "749",
        "289": "428",
        "29": "254",
        "290": "57",
        "291": "1639",
        "292": "1935",
        "293": "2111",
        "294": "1606",
        "295": "1926",
        "296": null,
        "297": "1807",
        "298": "1510",
        "299": "537",
        "3": "433",
        "30": "571",
        "300": null,
        "301": "1712",
        "302": "1352",
        "303": null,
        "304": "961",
        "305": null,
        "306": "160",
        "307": "675",
        "308": "1138",
        "309": "202",
        "31": "315",
        "310": "698",
        "311": "709",
        "312": "520",
        "313": "1767",
        "314": "151",
        "315": "935",
        "316": "383",
        "317": null,
        "318": "1203",
        "319": "579",
        "32": "1122",
        "320": "1779",
        "321": "1790",
        "322": "172",
        "323": "2014",
        "324": "775",
        "325": "887",
        "326": "746",
        "327": "1152",
        "328": "1426",
        "329": "517",
        "33": "1708",
        "330": "2070",
        "331": null,
        "332": "995",
        "333": "716",
        "334": "1381",
        "335": null,
        "336": "1588",
        "337": "1474",
        "338": "171",
        "339": "1954",
        "34": "1155",
        "340": "2080",
        "341": "309",
        "342": "1192",
        "343": "1551",
        "344": "101",
        "345": null,
        "346": "582",
        "347": "1865",
        "348": "1969",
        "349": "1207",
        "35": "1982",
        "350": "1044",
        "351": "717",
        "352": "1907",
        "353": "1443",
        "354": "259",
        "355": "133",
        "356": "1089",
        "357": "1772",
        "358": "1188",
        "359": "153",
        "36": "2096",
        "360": "1205",
        "361": "329",
        "362": "844",
        "363": "1242",
        "364": "1465",
        "365": "1868",
        "366": null,
        "367": "880",
        "368": "1900",
        "369": "1434",
        "37": "490",
        "370": "1495",
        "371": "2082",
        "372": "1428",
        "373": "639",
        "374": null,
        "375": "1877",
        "376": "2143",
        "377": "1172",
        "378": "1774",
        "379": "549",
        "38": null,
        "380": null,
        "381": "1669",
        "382": null,
        "383": "913",
        "384": "603",
        "385": "1526",
        "386": "1472",
        "387": "1406",
        "388": "2084",
        "389": "705",
        "39": "1262",
        "390": "600",
        "391": null,
        "392": "1778",
        "393": "1925",
        "394": "229",
        "395": "911",
        "396": "2015",
        "397": null,
        "398": "439",
        "399": "2061",
        "4": "1592",
        "40": "255",
        "400": "423",
        "401": "1389",
        "402": "1760",
        "403": "1054",
        "404": "634",
        "405": "795",
        "406": "1020",
        "407": "956",
        "408": "461",
        "409": "534",
        "41": "1300",
        "410": null,
        "411": "1074",
        "412": "1619",
        "413": "1452",
        "414": "647",
        "415": null,
        "416": "108",
        "417": "1387",
        "418": "2078",
        "419": "1049",
        "42": null,
        "420": "819",
        "421": "892",
        "422": "1539",
        "423": null,
        "424": "8",
        "425": "2094",
        "426": "1951",
        "427": "1324",
        "428": "929",
        "429": "36",
        "43": "777",
        "430": "307",
        "431": "1154",
        "432": "706",
        "433": "1911",
        "434": "1993",
        "435": "1786",
        "436": "299",
        "437": "883",
        "438": "1668",
        "439": null,
        "44": "1308",
        "440": "436",
        "441": "102",
        "442": "1922",
        "443": "1312",
        "444": "1830",
        "445": "2169",
        "446": null,
        "447": "1157",
        "448": "1414",
        "449": "1117",
        "45": "858",
        "450": "898",
        "451": null,
        "452": "1976",
        "453": "1050",
        "454": "937",
        "455": "1268",
        "456": "1645",
        "457": null,
        "458": "1748",
        "459": "385",
        "46": "1384",
        "460": "1734",
        "461": "1291",
        "462": "1055",
        "463": "1013",
        "464": "366",
        "465": "2065",
        "466": "460",
        "467": "1275",
        "468": "336",
        "469": null,
        "47": "2154",
        "470": "446",
        "471": "117",
        "472": "951",
        "473": "1967",
        "474": "1537",
        "475": "449",
        "476": "2163",
        "477": "1427",
        "478": "856",
        "479": "1946",
        "48": "509",
        "480": "1070",
        "481": "938",
        "482": "1052",
        "483": "1653",
        "484": null,
        "485": "1576",
        "486": "1833",
        "487": "187",
        "488": "1244",
        "489": null,
        "49": "944",
        "490": null,
        "491": "263",
        "492": "1066",
        "493": "1691",
        "494": "372",
        "495": "857",
        "496": null,
        "497": "1897",
        "498": "734",
        "499": "396",
        "5": "755",
        "50": "405",
        "500": null,
        "501": "765",
        "502": "864",
        "503": "2120",
        "504": "970",
        "505": "1320",
        "506": "696",
        "507": "1891",
        "508": "1927",
        "509": "669",
        "51": "1766",
        "510": "1679",
        "511": "191",
        "512": "1294",
        "513": "1184",
        "514": "1914",
        "515": "1677",
        "516": "185",
        "517": "916",
        "518": "1036",
        "519": "270",
        "52": "802",
        "520": "644",
        "521": "943",
        "522": "1563",
        "523": null,
        "524": "1755",
        "525": "1296",
        "526": "71",
        "527": "445",
        "528": "1248",
        "529": "1781",
        "53": "1168",
        "530": "822",
        "531": "940",
        "532": "2113",
        "533": "430",
        "534": null,
        "535": "296",
        "536": "840",
        "537": "119",
        "538": "1189",
        "539": "650",
        "54": "2025",
        "540": "135",
        "541": "1977",
        "542": "641",
        "543": "1680",
        "544": null,
        "545": "1079",
        "546": null,
        "547": "94",
        "548": "369",
        "549": "1148",
        "55": "1762",
        "550": "1400",
        "551": "68",
        "552": "2037",
        "553": "354",
        "554": "250",
        "555": null,
        "556": "1397",
        "557": "2049",
        "558": "1274",
        "559": "1005",
        "56": "1649",
        "560": "1497",
        "561": "1664",
        "562": "1133",
        "563": "1410",
        "564": "806",
        "565": "807",
        "566": "561",
        "567": "577",
        "568": "22",
        "569": "837",
        "57": "642",
        "570": "223",
        "571": "646",
        "572": "1209",
        "573": "930",
        "574": "1134",
        "575": "1391",
        "576": "1844",
        "577": "977",
        "578": "629",
        "579": "1655",
        "58": "2075",
        "580": "182",
        "581": "2108",
        "582": "1813",
        "583": "2000",
        "584": null,
        "585": "854",
        "586": "1808",
        "587": "1131",
        "588": "879",
        "589": "1538",
        "59": "162",
        "590": "1556",
        "591": "175",
        "592": "832",
        "593": "1233",
        "594": "438",
        "595": "1217",
        "596": "2010",
        "597": "1339",
        "598": "1059",
        "599": "1999",
        "6": "1165",
        "60": "962",
        "600": "1959",
        "601": null,
        "602": "572",
        "603": "1196",
        "604": "627",
        "605": "767",
        "606": "1435",
        "607": "1519",
        "608": "1380",
        "609": "1584",
        "61": "121",
        "610": null,
        "611": "578",
        "612": "1221",
        "613": "1247",
        "614": "1420",
        "615": "594",
        "616": "882",
        "617": "391",
        "618": "2159",
        "619": "1609",
        "62": null,
        "620": "357",
        "621": "568",
        "622": "37",
        "623": "1208",
        "624": "1979",
        "625": "373",
        "626": null,
        "627": "850",
        "628": "1820",
        "629": "415",
        "63": "1279",
        "630": "681",
        "631": "2095",
        "632": "1810",
        "633": "667",
        "634": "1376",
        "635": "136",
        "636": "463",
        "637": "1151",
        "638": "1881",
        "639": "1364",
        "64": "503",
        "640": "997",
        "641": "619",
        "642": "1545",
        "643": "1346",
        "644": "1866",
        "645": "1218",
        "646": "465",
        "647": null,
        "648": "1460",
        "649": "1736",
        "65": "1332",
        "650": "235",
        "651": null,
        "652": "1981",
        "653": null,
        "654": null,
        "655": "967",
        "656": "1809",
        "657": "238",
        "658": null,
        "659": "184",
        "66": "483",
        "660": "407",
        "661": "2028",
        "662": null,
        "663": "265",
        "664": "959",
        "665": "1955",
        "666": "1164",
        "667": "731",
        "668": "1302",
        "669": null,
        "67": "419",
        "670": "732",
        "671": "467",
        "672": "692",
        "673": "1415",
        "674": "1533",
        "675": "116",
        "676": "1690",
        "677": "1583",
        "678": "685",
        "679": "1265",
        "68": "1612",
        "680": "325",
        "681": "893",
        "682": "1299",
        "683": "318",
        "684": "1108",
        "685": "2026",
        "686": "2035",
        "687": "242",
        "688": "2132",
        "689": "1978",
        "69": "1422",
        "690": "1929",
        "691": "2021",
        "692": "404",
        "693": "1484",
        "694": "576",
        "695": "45",
        "696": "237",
        "697": "1855",
        "698": "1647",
        "699": "44",
        "7": "1701",
        "70": "1185",
        "700": null,
        "701": "686",
        "702": "477",
        "703": "111",
        "704": null,
        "705": "1513",
        "706": "1158",
        "707": "1046",
        "708": "1689",
        "709": null,
        "71": "1848",
        "710": "1564",
        "711": "2012",
        "712": null,
        "713": "1077",
        "714": "1219",
        "715": "1771",
        "716": "1245",
        "717": "1709",
        "718": "1107",
        "719": "2074",
        "72": "1638",
        "720": "1746",
        "721": "211",
        "722": "2071",
        "723": "948",
        "724": null,
        "725": "458",
        "726": "1467",
        "727": "1913",
        "728": "811",
        "729": "1611",
        "73": null,
        "730": "2109",
        "731": "1001",
        "732": "234",
        "733": "797",
        "734": "1094",
        "735": null,
        "736": "1853",
        "737": "1177",
        "738": "300",
        "739": null,
        "74": "527",
        "740": "500",
        "741": "570",
        "742": "1550",
        "743": "1160",
        "744": "1765",
        "745": "666",
        "746": "1173",
        "747": "1871",
        "748": "1321",
        "749": "1856",
        "75": "1362",
        "750": "1500",
        "751": "105",
        "752": null,
        "753": "719",
        "754": "697",
        "755": "1585",
        "756": "148",
        "757": "1737",
        "758": "1379",
        "759": "194",
        "76": "1083",
        "760": "574",
        "761": null,
        "762": "1756",
        "763": "596",
        "764": "1867",
        "765": "1214",
        "766": "936",
        "767": null,
        "768": "1941",
        "769": "1486",
        "77": null,
        "770": null,
        "771": "2066",
        "772": "233",
        "773": null,
        "774": "281",
        "775": "2133",
        "776": null,
        "777": null,
        "778": "1471",
        "779": "691",
        "78": "440",
        "780": "789",
        "79": "1315",
        "8": "1601",
        "80": "83",
        "81": "1565",
        "82": "1985",
        "83": "1118",
        "84": "406",
        "85": "981",
        "86": "239",
        "87": "714",
        "88": "868",
        "89": null,
        "9": "1411",
        "90": "922",
        "91": "1097",
        "92": "899",
        "93": "1390",
        "94": "474",
        "95": null,
        "96": "86",
        "97": "1730",
        "98": null,
        "99": "1143"
    }
}