[
    {
        "OBP_res": 8798.33,
        "OBP_time": 2.88011932,
        "QAP_res": 17034.405,
        "QAP_time": 0.01414251,
        "id": 4
    },
    {
        "OBP_res": 8743.486,
        "OBP_time": 2.06621361,
        "QAP_res": 17099.513,
        "QAP_time": 0.01391602,
        "id": 9
    },
    {
        "OBP_res": 8799.92,
        "OBP_time": 2.01178217,
        "QAP_res": 17125.716,
        "QAP_time": 0.01420546,
        "id": 13
    },
    {
        "OBP_res": 8603.688,
        "OBP_time": 1.93190169,
        "QAP_res": 17149.671,
        "QAP_time": 0.01385164,
        "id": 1
    },
    {
        "OBP_res": 8816.33,
        "OBP_time": 2.03353643,
        "QAP_res": 17188.084,
        "QAP_time": 0.01381135,
        "id": 15
    },
    {
        "OBP_res": 8560.301,
        "OBP_time": 1.93082237,
        "QAP_res": 17279.418,
        "QAP_time": 0.0142312,
        "id": 12
    },
    {
        "OBP_res": 9023.373,
        "OBP_time": 2.0983758,
        "QAP_res": 17341.683,
        "QAP_time": 0.01384711,
        "id": 0
    },
    {
        "OBP_res": 8680.758,
        "OBP_time": 2.44583344,
        "QAP_res": 17345.15,
        "QAP_time": 0.01384354,
        "id": 10
    },
    {
        "OBP_res": 8776.266,
        "OBP_time": 2.1495316,
        "QAP_res": 17347.138,
        "QAP_time": 0.01383924,
        "id": 3
    },
    {
        "OBP_res": 8582.225,
        "OBP_time": 2.04023075,
        "QAP_res": 17411.542,
        "QAP_time": 0.01426482,
        "id": 14
    },
    {
        "OBP_res": 8552.959,
        "OBP_time": 1.94854617,
        "QAP_res": 17422.927,
        "QAP_time": 0.01385188,
        "id": 2
    },
    {
        "OBP_res": 8663.803,
        "OBP_time": 1.96637154,
        "QAP_res": 17429.7,
        "QAP_time": 0.01376557,
        "id": 8
    },
    {
        "OBP_res": 8615.941,
        "OBP_time": 2.02704287,
        "QAP_res": 17467.918,
        "QAP_time": 0.01378393,
        "id": 5
    },
    {
        "OBP_res": 8512.922,
        "OBP_time": 1.97477317,
        "QAP_res": 17470.601,
        "QAP_time": 0.01420355,
        "id": 11
    },
    {
        "OBP_res": 8806.107,
        "OBP_time": 1.99794626,
        "QAP_res": 17475.642,
        "QAP_time": 0.01384258,
        "id": 16
    },
    {
        "OBP_res": 8656.355,
        "OBP_time": 2.56338143,
        "QAP_res": 17509.555,
        "QAP_time": 0.01393914,
        "id": 18
    },
    {
        "OBP_res": 8585.957,
        "OBP_time": 2.05285954,
        "QAP_res": 17567.957,
        "QAP_time": 0.01377392,
        "id": 17
    },
    {
        "OBP_res": 8815.865,
        "OBP_time": 2.50404716,
        "QAP_res": 17592.336,
        "QAP_time": 0.01414514,
        "id": 7
    },
    {
        "OBP_res": 8867.287,
        "OBP_time": 2.38329053,
        "QAP_res": 17796.677,
        "QAP_time": 0.01383734,
        "id": 19
    },
    {
        "OBP_res": 8903.508,
        "OBP_time": 2.02524996,
        "QAP_res": 17836.236,
        "QAP_time": 0.01378894,
        "id": 6
    }
]