{
    "10": 171,
    "11": 236,
    "12": 247,
    "13": 169,
    "14": 243,
    "15": 220,
    "16": 289,
    "17": 467,
    "18": 83,
    "19": 6,
    "2": 471,
    "20": 423,
    "21": 161,
    "22": 189,
    "23": 190,
    "24": 406,
    "25": 22,
    "26": 381,
    "27": 76,
    "28": 45,
    "29": 234,
    "3": 425,
    "30": 207,
    "31": 113,
    "32": 475,
    "33": 376,
    "34": 468,
    "35": 320,
    "36": 210,
    "37": 452,
    "38": 59,
    "39": 327,
    "4": 248,
    "40": 290,
    "41": 188,
    "42": 14,
    "43": 413,
    "44": 334,
    "45": 272,
    "46": 201,
    "47": 93,
    "48": 387,
    "49": 165,
    "5": 69,
    "50": 295,
    "6": 175,
    "7": 465,
    "8": 382,
    "9": 109
}