{
    "ASSIGNMENT_OPTIONS": {
        "assignmentType": "firstAssignment",
        "evaluationData": "pickingLog",
        "openLocations": "allExceptPickingLog"
    },
    "CAPACITIES": 26,
    "DATA_SECTION": "",
    "HEADER": {
        "COMMENTS": {
            "Best known objective": "4066.195",
            "Computational time (s)": "22.19279718399048",
            "descr": "Modified TSPLIB for the SLAP"
        },
        "VERSION": "SLAP 1.0"
    },
    "NAME": "c689_add1",
    "NUM_CAPACITIES": 1,
    "NUM_VEHICLES": 18,
    "NUM_VISITS": 689,
    "ORDERS": {
        "1": [
            "2",
            "3"
        ],
        "10": [
            "18",
            "19"
        ],
        "100": [
            "154"
        ],
        "101": [
            "155",
            "156"
        ],
        "102": [
            "157"
        ],
        "103": [
            "158",
            "159"
        ],
        "104": [
            "160",
            "161"
        ],
        "105": [
            "162",
            "163"
        ],
        "106": [
            "164",
            "165"
        ],
        "107": [
            "166",
            "167"
        ],
        "108": [
            "168",
            "169"
        ],
        "109": [
            "170"
        ],
        "11": [
            "20"
        ],
        "110": [
            "171"
        ],
        "111": [
            "172",
            "173"
        ],
        "112": [
            "174",
            "175"
        ],
        "113": [
            "176"
        ],
        "114": [
            "177"
        ],
        "115": [
            "178",
            "179"
        ],
        "116": [
            "180"
        ],
        "117": [
            "181"
        ],
        "118": [
            "182",
            "183"
        ],
        "119": [
            "184"
        ],
        "12": [
            "21"
        ],
        "120": [
            "185",
            "186"
        ],
        "121": [
            "187"
        ],
        "122": [
            "188"
        ],
        "123": [
            "189",
            "190"
        ],
        "124": [
            "191",
            "192"
        ],
        "125": [
            "193",
            "194"
        ],
        "126": [
            "195",
            "196"
        ],
        "127": [
            "197",
            "198"
        ],
        "128": [
            "199",
            "200"
        ],
        "129": [
            "201",
            "202"
        ],
        "13": [
            "22"
        ],
        "130": [
            "203",
            "204"
        ],
        "131": [
            "205"
        ],
        "132": [
            "206"
        ],
        "133": [
            "207",
            "208"
        ],
        "134": [
            "209",
            "210"
        ],
        "135": [
            "211"
        ],
        "136": [
            "212"
        ],
        "137": [
            "213"
        ],
        "138": [
            "214"
        ],
        "139": [
            "215"
        ],
        "14": [
            "23",
            "24"
        ],
        "140": [
            "216",
            "217"
        ],
        "141": [
            "218"
        ],
        "142": [
            "219",
            "220"
        ],
        "143": [
            "221"
        ],
        "144": [
            "222"
        ],
        "145": [
            "223",
            "224"
        ],
        "146": [
            "225"
        ],
        "147": [
            "226",
            "227"
        ],
        "148": [
            "228"
        ],
        "149": [
            "229",
            "230"
        ],
        "15": [
            "25"
        ],
        "150": [
            "231",
            "232"
        ],
        "151": [
            "233",
            "234"
        ],
        "152": [
            "235",
            "236"
        ],
        "153": [
            "237"
        ],
        "154": [
            "238",
            "239"
        ],
        "155": [
            "240",
            "178"
        ],
        "156": [
            "241",
            "242"
        ],
        "157": [
            "243"
        ],
        "158": [
            "244",
            "245"
        ],
        "159": [
            "246",
            "247"
        ],
        "16": [
            "26",
            "27"
        ],
        "160": [
            "248"
        ],
        "161": [
            "249"
        ],
        "162": [
            "250"
        ],
        "163": [
            "251",
            "252"
        ],
        "164": [
            "253"
        ],
        "165": [
            "254",
            "255"
        ],
        "166": [
            "256",
            "257"
        ],
        "167": [
            "258"
        ],
        "168": [
            "259",
            "260"
        ],
        "169": [
            "261",
            "262"
        ],
        "17": [
            "28",
            "29"
        ],
        "170": [
            "263",
            "264"
        ],
        "171": [
            "265",
            "266"
        ],
        "172": [
            "267"
        ],
        "173": [
            "268",
            "269"
        ],
        "174": [
            "270",
            "271"
        ],
        "175": [
            "272",
            "273"
        ],
        "176": [
            "274",
            "275"
        ],
        "177": [
            "276"
        ],
        "178": [
            "277"
        ],
        "179": [
            "278",
            "279"
        ],
        "18": [
            "30",
            "31"
        ],
        "180": [
            "280",
            "281"
        ],
        "181": [
            "282",
            "283"
        ],
        "182": [
            "284",
            "285"
        ],
        "183": [
            "286",
            "287"
        ],
        "184": [
            "288",
            "289"
        ],
        "185": [
            "290",
            "291"
        ],
        "186": [
            "292",
            "293"
        ],
        "187": [
            "294"
        ],
        "188": [
            "295"
        ],
        "189": [
            "296",
            "297"
        ],
        "19": [
            "32",
            "33"
        ],
        "190": [
            "298"
        ],
        "191": [
            "299"
        ],
        "192": [
            "300",
            "301"
        ],
        "193": [
            "302",
            "303"
        ],
        "194": [
            "304"
        ],
        "195": [
            "305"
        ],
        "196": [
            "306",
            "307"
        ],
        "197": [
            "308",
            "309"
        ],
        "198": [
            "310",
            "311"
        ],
        "199": [
            "312",
            "313"
        ],
        "2": [
            "4",
            "5"
        ],
        "20": [
            "34",
            "35"
        ],
        "200": [
            "314",
            "315"
        ],
        "201": [
            "316",
            "317"
        ],
        "202": [
            "318"
        ],
        "203": [
            "319",
            "320"
        ],
        "204": [
            "321"
        ],
        "205": [
            "322",
            "323"
        ],
        "206": [
            "324"
        ],
        "207": [
            "325"
        ],
        "208": [
            "326"
        ],
        "209": [
            "327"
        ],
        "21": [
            "36"
        ],
        "210": [
            "328"
        ],
        "211": [
            "329"
        ],
        "212": [
            "330",
            "331"
        ],
        "213": [
            "332"
        ],
        "214": [
            "333"
        ],
        "215": [
            "334",
            "335"
        ],
        "216": [
            "336"
        ],
        "217": [
            "337"
        ],
        "218": [
            "338"
        ],
        "219": [
            "339",
            "340"
        ],
        "22": [
            "37",
            "38"
        ],
        "220": [
            "341"
        ],
        "221": [
            "342",
            "343"
        ],
        "222": [
            "344"
        ],
        "223": [
            "345",
            "346"
        ],
        "224": [
            "347",
            "348"
        ],
        "225": [
            "349",
            "350"
        ],
        "226": [
            "351",
            "352"
        ],
        "227": [
            "353",
            "354"
        ],
        "228": [
            "355"
        ],
        "229": [
            "356"
        ],
        "23": [
            "39"
        ],
        "230": [
            "357",
            "358"
        ],
        "231": [
            "359"
        ],
        "232": [
            "360"
        ],
        "233": [
            "361"
        ],
        "234": [
            "362",
            "363"
        ],
        "235": [
            "364"
        ],
        "236": [
            "365",
            "366"
        ],
        "237": [
            "367",
            "368"
        ],
        "238": [
            "369",
            "370"
        ],
        "239": [
            "371"
        ],
        "24": [
            "40"
        ],
        "240": [
            "372",
            "373"
        ],
        "241": [
            "374"
        ],
        "242": [
            "375",
            "376"
        ],
        "243": [
            "377",
            "378"
        ],
        "244": [
            "379",
            "380"
        ],
        "245": [
            "381",
            "382"
        ],
        "246": [
            "383"
        ],
        "247": [
            "384"
        ],
        "248": [
            "385"
        ],
        "249": [
            "386"
        ],
        "25": [
            "41"
        ],
        "250": [
            "387",
            "388"
        ],
        "251": [
            "389"
        ],
        "252": [
            "390"
        ],
        "253": [
            "391"
        ],
        "254": [
            "392",
            "393"
        ],
        "255": [
            "394"
        ],
        "256": [
            "395"
        ],
        "257": [
            "396",
            "397"
        ],
        "258": [
            "398"
        ],
        "259": [
            "399",
            "400"
        ],
        "26": [
            "42"
        ],
        "260": [
            "401",
            "402"
        ],
        "261": [
            "403"
        ],
        "262": [
            "404",
            "405"
        ],
        "263": [
            "406"
        ],
        "264": [
            "407"
        ],
        "265": [
            "408",
            "409"
        ],
        "266": [
            "410",
            "411"
        ],
        "267": [
            "412"
        ],
        "268": [
            "413",
            "414"
        ],
        "269": [
            "415"
        ],
        "27": [
            "43"
        ],
        "270": [
            "416"
        ],
        "271": [
            "417"
        ],
        "272": [
            "418"
        ],
        "273": [
            "419",
            "420"
        ],
        "274": [
            "421"
        ],
        "275": [
            "422",
            "423",
            "302"
        ],
        "276": [
            "424",
            "425"
        ],
        "277": [
            "426"
        ],
        "278": [
            "427"
        ],
        "279": [
            "428",
            "429"
        ],
        "28": [
            "44"
        ],
        "280": [
            "430"
        ],
        "281": [
            "431"
        ],
        "282": [
            "432",
            "433"
        ],
        "283": [
            "434"
        ],
        "284": [
            "435",
            "436"
        ],
        "285": [
            "437",
            "438"
        ],
        "286": [
            "439",
            "440"
        ],
        "287": [
            "441",
            "442"
        ],
        "288": [
            "443",
            "444"
        ],
        "289": [
            "445",
            "446"
        ],
        "29": [
            "45"
        ],
        "290": [
            "447",
            "448"
        ],
        "291": [
            "449"
        ],
        "292": [
            "450"
        ],
        "293": [
            "451"
        ],
        "294": [
            "452",
            "453"
        ],
        "295": [
            "454"
        ],
        "296": [
            "455"
        ],
        "297": [
            "456",
            "457"
        ],
        "298": [
            "458"
        ],
        "299": [
            "459"
        ],
        "3": [
            "6",
            "7"
        ],
        "30": [
            "46",
            "47",
            "20"
        ],
        "300": [
            "460",
            "461"
        ],
        "301": [
            "462"
        ],
        "302": [
            "463",
            "464"
        ],
        "303": [
            "465",
            "466"
        ],
        "304": [
            "467"
        ],
        "305": [
            "468"
        ],
        "306": [
            "469",
            "470"
        ],
        "307": [
            "471",
            "472"
        ],
        "308": [
            "473"
        ],
        "309": [
            "474"
        ],
        "31": [
            "48",
            "49"
        ],
        "310": [
            "475"
        ],
        "311": [
            "476",
            "477"
        ],
        "312": [
            "478"
        ],
        "313": [
            "479"
        ],
        "314": [
            "480",
            "481"
        ],
        "315": [
            "482"
        ],
        "316": [
            "483"
        ],
        "317": [
            "484"
        ],
        "318": [
            "485",
            "486"
        ],
        "319": [
            "487",
            "488"
        ],
        "32": [
            "50",
            "51"
        ],
        "320": [
            "489"
        ],
        "321": [
            "490"
        ],
        "322": [
            "491"
        ],
        "323": [
            "492"
        ],
        "324": [
            "493",
            "494"
        ],
        "325": [
            "495"
        ],
        "326": [
            "496"
        ],
        "327": [
            "497"
        ],
        "328": [
            "498"
        ],
        "329": [
            "499"
        ],
        "33": [
            "52",
            "53"
        ],
        "330": [
            "500"
        ],
        "331": [
            "501",
            "502"
        ],
        "332": [
            "503"
        ],
        "333": [
            "504"
        ],
        "334": [
            "505",
            "506"
        ],
        "335": [
            "507",
            "508"
        ],
        "336": [
            "509",
            "510"
        ],
        "337": [
            "511"
        ],
        "338": [
            "512"
        ],
        "339": [
            "513",
            "514"
        ],
        "34": [
            "54",
            "55"
        ],
        "340": [
            "515",
            "516"
        ],
        "341": [
            "517",
            "518"
        ],
        "342": [
            "519"
        ],
        "343": [
            "520"
        ],
        "344": [
            "521"
        ],
        "345": [
            "522"
        ],
        "346": [
            "523"
        ],
        "347": [
            "524",
            "525"
        ],
        "348": [
            "526"
        ],
        "349": [
            "527"
        ],
        "35": [
            "56",
            "57"
        ],
        "350": [
            "528",
            "529"
        ],
        "351": [
            "530",
            "531"
        ],
        "352": [
            "532",
            "533"
        ],
        "353": [
            "534"
        ],
        "354": [
            "535",
            "536"
        ],
        "355": [
            "537",
            "538"
        ],
        "356": [
            "539",
            "540"
        ],
        "357": [
            "541",
            "542"
        ],
        "358": [
            "543",
            "544"
        ],
        "359": [
            "545"
        ],
        "36": [
            "58",
            "59"
        ],
        "360": [
            "546",
            "547"
        ],
        "361": [
            "548"
        ],
        "362": [
            "549",
            "550"
        ],
        "363": [
            "551"
        ],
        "364": [
            "552"
        ],
        "365": [
            "553",
            "554"
        ],
        "366": [
            "555",
            "556"
        ],
        "367": [
            "557",
            "558"
        ],
        "368": [
            "559",
            "560"
        ],
        "369": [
            "561"
        ],
        "37": [
            "60",
            "61"
        ],
        "370": [
            "562",
            "563"
        ],
        "371": [
            "564"
        ],
        "372": [
            "565"
        ],
        "373": [
            "566"
        ],
        "374": [
            "567"
        ],
        "375": [
            "568"
        ],
        "376": [
            "569"
        ],
        "377": [
            "570"
        ],
        "378": [
            "571"
        ],
        "379": [
            "572"
        ],
        "38": [
            "62",
            "63"
        ],
        "380": [
            "573"
        ],
        "381": [
            "574"
        ],
        "382": [
            "575",
            "576"
        ],
        "383": [
            "577",
            "578"
        ],
        "384": [
            "579"
        ],
        "385": [
            "580",
            "581"
        ],
        "386": [
            "582",
            "583"
        ],
        "387": [
            "584"
        ],
        "388": [
            "585",
            "586"
        ],
        "389": [
            "587",
            "588"
        ],
        "39": [
            "64"
        ],
        "390": [
            "589"
        ],
        "391": [
            "590",
            "591"
        ],
        "392": [
            "592"
        ],
        "393": [
            "593",
            "594"
        ],
        "394": [
            "595"
        ],
        "395": [
            "596",
            "597"
        ],
        "396": [
            "598"
        ],
        "397": [
            "599",
            "600"
        ],
        "398": [
            "601"
        ],
        "399": [
            "602",
            "603"
        ],
        "4": [
            "8",
            "9"
        ],
        "40": [
            "65",
            "66"
        ],
        "400": [
            "604"
        ],
        "401": [
            "605",
            "606"
        ],
        "402": [
            "607"
        ],
        "403": [
            "608"
        ],
        "404": [
            "609",
            "610"
        ],
        "405": [
            "611"
        ],
        "406": [
            "612"
        ],
        "407": [
            "613"
        ],
        "408": [
            "614"
        ],
        "409": [
            "615",
            "616"
        ],
        "41": [
            "67"
        ],
        "410": [
            "617",
            "618"
        ],
        "411": [
            "619",
            "620"
        ],
        "412": [
            "621",
            "622"
        ],
        "413": [
            "623"
        ],
        "414": [
            "624",
            "625"
        ],
        "415": [
            "626"
        ],
        "416": [
            "627"
        ],
        "417": [
            "628",
            "629"
        ],
        "418": [
            "630",
            "631"
        ],
        "419": [
            "632"
        ],
        "42": [
            "68"
        ],
        "420": [
            "633",
            "634"
        ],
        "421": [
            "635",
            "636"
        ],
        "422": [
            "637"
        ],
        "423": [
            "638",
            "639"
        ],
        "424": [
            "640"
        ],
        "425": [
            "641"
        ],
        "426": [
            "642"
        ],
        "427": [
            "643"
        ],
        "428": [
            "644",
            "645"
        ],
        "429": [
            "646"
        ],
        "43": [
            "69"
        ],
        "430": [
            "647"
        ],
        "431": [
            "648"
        ],
        "432": [
            "649"
        ],
        "433": [
            "650",
            "651"
        ],
        "434": [
            "652",
            "653"
        ],
        "435": [
            "654",
            "655"
        ],
        "436": [
            "656"
        ],
        "437": [
            "657"
        ],
        "438": [
            "658",
            "659"
        ],
        "439": [
            "660",
            "661"
        ],
        "44": [
            "70"
        ],
        "440": [
            "662"
        ],
        "441": [
            "663",
            "664"
        ],
        "442": [
            "665",
            "666"
        ],
        "443": [
            "667",
            "668"
        ],
        "444": [
            "669"
        ],
        "445": [
            "670"
        ],
        "446": [
            "671"
        ],
        "447": [
            "672",
            "673"
        ],
        "448": [
            "674"
        ],
        "449": [
            "675"
        ],
        "45": [
            "71"
        ],
        "450": [
            "676",
            "677"
        ],
        "451": [
            "678",
            "679"
        ],
        "452": [
            "680"
        ],
        "453": [
            "681"
        ],
        "454": [
            "682",
            "683"
        ],
        "46": [
            "72"
        ],
        "47": [
            "73"
        ],
        "48": [
            "74"
        ],
        "49": [
            "75"
        ],
        "5": [
            "10",
            "11"
        ],
        "50": [
            "76"
        ],
        "51": [
            "77",
            "78"
        ],
        "52": [
            "79",
            "80"
        ],
        "53": [
            "81",
            "82"
        ],
        "54": [
            "83",
            "84",
            "667"
        ],
        "55": [
            "85",
            "86"
        ],
        "56": [
            "87",
            "412"
        ],
        "57": [
            "88"
        ],
        "58": [
            "89",
            "90"
        ],
        "59": [
            "91",
            "92"
        ],
        "6": [
            "12",
            "13"
        ],
        "60": [
            "93"
        ],
        "61": [
            "94"
        ],
        "62": [
            "95",
            "96"
        ],
        "63": [
            "97",
            "98"
        ],
        "64": [
            "99",
            "100"
        ],
        "65": [
            "101",
            "102"
        ],
        "66": [
            "103"
        ],
        "67": [
            "104",
            "105"
        ],
        "68": [
            "106",
            "107"
        ],
        "69": [
            "108",
            "109"
        ],
        "7": [
            "14"
        ],
        "70": [
            "110",
            "41"
        ],
        "71": [
            "111"
        ],
        "72": [
            "112"
        ],
        "73": [
            "113",
            "114"
        ],
        "74": [
            "115"
        ],
        "75": [
            "116"
        ],
        "76": [
            "117"
        ],
        "77": [
            "118"
        ],
        "78": [
            "119",
            "120"
        ],
        "79": [
            "121",
            "122"
        ],
        "8": [
            "15",
            "16"
        ],
        "80": [
            "123",
            "124"
        ],
        "81": [
            "125",
            "126"
        ],
        "82": [
            "127",
            "128"
        ],
        "83": [
            "129"
        ],
        "84": [
            "130",
            "131"
        ],
        "85": [
            "132"
        ],
        "86": [
            "133"
        ],
        "87": [
            "134",
            "478"
        ],
        "88": [
            "135",
            "136"
        ],
        "89": [
            "137"
        ],
        "9": [
            "17"
        ],
        "90": [
            "138",
            "139"
        ],
        "91": [
            "140",
            "141"
        ],
        "92": [
            "142",
            "143"
        ],
        "93": [
            "144"
        ],
        "94": [
            "145"
        ],
        "95": [
            "146"
        ],
        "96": [
            "147",
            "148"
        ],
        "97": [
            "149",
            "150"
        ],
        "98": [
            "151",
            "152"
        ],
        "99": [
            "153"
        ]
    },
    "SKUS_TO_SLOT": [
        "3",
        "19",
        "163",
        "166",
        "168",
        "21",
        "185",
        "191",
        "199",
        "206",
        "234",
        "243",
        "244",
        "255",
        "258",
        "266",
        "290",
        "292",
        "301",
        "307",
        "309",
        "36",
        "336",
        "346",
        "347",
        "354",
        "364",
        "379",
        "380",
        "399",
        "414",
        "433",
        "448",
        "7",
        "474",
        "483",
        "51",
        "500",
        "511",
        "54",
        "528",
        "532",
        "533",
        "552",
        "553",
        "61",
        "565",
        "568",
        "579",
        "590",
        "8",
        "604",
        "616",
        "620",
        "621",
        "623",
        "625",
        "632",
        "633",
        "642",
        "653",
        "655",
        "681",
        "78",
        "667",
        "105",
        "110",
        "15",
        "133",
        "139"
    ],
    "TIMESTEP": "1",
    "TIME_AVAIL_SECTION": {
        "1": "1",
        "10": "1",
        "100": "1",
        "101": "1",
        "102": "1",
        "103": "1",
        "104": "1",
        "105": "1",
        "106": "1",
        "107": "1",
        "108": "1",
        "109": "1",
        "11": "1",
        "110": "1",
        "111": "1",
        "112": "1",
        "113": "1",
        "114": "1",
        "115": "1",
        "116": "1",
        "117": "1",
        "118": "1",
        "119": "1",
        "12": "1",
        "120": "1",
        "121": "1",
        "122": "1",
        "123": "1",
        "124": "1",
        "125": "1",
        "126": "1",
        "127": "1",
        "128": "1",
        "129": "1",
        "13": "1",
        "130": "1",
        "131": "1",
        "132": "1",
        "133": "1",
        "134": "1",
        "135": "1",
        "136": "1",
        "137": "1",
        "138": "1",
        "139": "1",
        "14": "1",
        "140": "1",
        "141": "1",
        "142": "1",
        "143": "1",
        "144": "1",
        "145": "1",
        "146": "1",
        "147": "1",
        "148": "1",
        "149": "1",
        "15": "1",
        "150": "1",
        "151": "1",
        "152": "1",
        "153": "1",
        "154": "1",
        "155": "1",
        "156": "1",
        "157": "1",
        "158": "1",
        "159": "1",
        "16": "1",
        "160": "1",
        "161": "1",
        "162": "1",
        "163": "1",
        "164": "1",
        "165": "1",
        "166": "1",
        "167": "1",
        "168": "1",
        "169": "1",
        "17": "1",
        "170": "1",
        "171": "1",
        "172": "1",
        "173": "1",
        "174": "1",
        "175": "1",
        "176": "1",
        "177": "1",
        "178": "1",
        "179": "1",
        "18": "1",
        "180": "1",
        "181": "1",
        "182": "1",
        "183": "1",
        "184": "1",
        "185": "1",
        "186": "1",
        "187": "1",
        "188": "1",
        "189": "1",
        "19": "1",
        "190": "1",
        "191": "1",
        "192": "1",
        "193": "1",
        "194": "1",
        "195": "1",
        "196": "1",
        "197": "1",
        "198": "1",
        "199": "1",
        "2": "1",
        "20": "1",
        "200": "1",
        "201": "1",
        "202": "1",
        "203": "1",
        "204": "1",
        "205": "1",
        "206": "1",
        "207": "1",
        "208": "1",
        "209": "1",
        "21": "1",
        "210": "1",
        "211": "1",
        "212": "1",
        "213": "1",
        "214": "1",
        "215": "1",
        "216": "1",
        "217": "1",
        "218": "1",
        "219": "1",
        "22": "1",
        "220": "1",
        "221": "1",
        "222": "1",
        "223": "1",
        "224": "1",
        "225": "1",
        "226": "1",
        "227": "1",
        "228": "1",
        "229": "1",
        "23": "1",
        "230": "1",
        "231": "1",
        "232": "1",
        "233": "1",
        "234": "1",
        "235": "1",
        "236": "1",
        "237": "1",
        "238": "1",
        "239": "1",
        "24": "1",
        "240": "1",
        "241": "1",
        "242": "1",
        "243": "1",
        "244": "1",
        "245": "1",
        "246": "1",
        "247": "1",
        "248": "1",
        "249": "1",
        "25": "1",
        "250": "1",
        "251": "1",
        "252": "1",
        "253": "1",
        "254": "1",
        "255": "1",
        "256": "1",
        "257": "1",
        "258": "1",
        "259": "1",
        "26": "1",
        "260": "1",
        "261": "1",
        "262": "1",
        "263": "1",
        "264": "1",
        "265": "1",
        "266": "1",
        "267": "1",
        "268": "1",
        "269": "1",
        "27": "1",
        "270": "1",
        "271": "1",
        "272": "1",
        "273": "1",
        "274": "1",
        "275": "1",
        "276": "1",
        "277": "1",
        "278": "1",
        "279": "1",
        "28": "1",
        "280": "1",
        "281": "1",
        "282": "1",
        "283": "1",
        "284": "1",
        "285": "1",
        "286": "1",
        "287": "1",
        "288": "1",
        "289": "1",
        "29": "1",
        "290": "1",
        "291": "1",
        "292": "1",
        "293": "1",
        "294": "1",
        "295": "1",
        "296": "1",
        "297": "1",
        "298": "1",
        "299": "1",
        "3": "1",
        "30": "1",
        "300": "1",
        "301": "1",
        "302": "1",
        "303": "1",
        "304": "1",
        "305": "1",
        "306": "1",
        "307": "1",
        "308": "1",
        "309": "1",
        "31": "1",
        "310": "1",
        "311": "1",
        "312": "1",
        "313": "1",
        "314": "1",
        "315": "1",
        "316": "1",
        "317": "1",
        "318": "1",
        "319": "1",
        "32": "1",
        "320": "1",
        "321": "1",
        "322": "1",
        "323": "1",
        "324": "1",
        "325": "1",
        "326": "1",
        "327": "1",
        "328": "1",
        "329": "1",
        "33": "1",
        "330": "1",
        "331": "1",
        "332": "1",
        "333": "1",
        "334": "1",
        "335": "1",
        "336": "1",
        "337": "1",
        "338": "1",
        "339": "1",
        "34": "1",
        "340": "1",
        "341": "1",
        "342": "1",
        "343": "1",
        "344": "1",
        "345": "1",
        "346": "1",
        "347": "1",
        "348": "1",
        "349": "1",
        "35": "1",
        "350": "1",
        "351": "1",
        "352": "1",
        "353": "1",
        "354": "1",
        "355": "1",
        "356": "1",
        "357": "1",
        "358": "1",
        "359": "1",
        "36": "1",
        "360": "1",
        "361": "1",
        "362": "1",
        "363": "1",
        "364": "1",
        "365": "1",
        "366": "1",
        "367": "1",
        "368": "1",
        "369": "1",
        "37": "1",
        "370": "1",
        "371": "1",
        "372": "1",
        "373": "1",
        "374": "1",
        "375": "1",
        "376": "1",
        "377": "1",
        "378": "1",
        "379": "1",
        "38": "1",
        "380": "1",
        "381": "1",
        "382": "1",
        "383": "1",
        "384": "1",
        "385": "1",
        "386": "1",
        "387": "1",
        "388": "1",
        "389": "1",
        "39": "1",
        "390": "1",
        "391": "1",
        "392": "1",
        "393": "1",
        "394": "1",
        "395": "1",
        "396": "1",
        "397": "1",
        "398": "1",
        "399": "1",
        "4": "1",
        "40": "1",
        "400": "1",
        "401": "1",
        "402": "1",
        "403": "1",
        "404": "1",
        "405": "1",
        "406": "1",
        "407": "1",
        "408": "1",
        "409": "1",
        "41": "1",
        "410": "1",
        "411": "1",
        "412": "1",
        "413": "1",
        "414": "1",
        "415": "1",
        "416": "1",
        "417": "1",
        "418": "1",
        "419": "1",
        "42": "1",
        "420": "1",
        "421": "1",
        "422": "1",
        "423": "1",
        "424": "1",
        "425": "1",
        "426": "1",
        "427": "1",
        "428": "1",
        "429": "1",
        "43": "1",
        "430": "1",
        "431": "1",
        "432": "1",
        "433": "1",
        "434": "1",
        "435": "1",
        "436": "1",
        "437": "1",
        "438": "1",
        "439": "1",
        "44": "1",
        "440": "1",
        "441": "1",
        "442": "1",
        "443": "1",
        "444": "1",
        "445": "1",
        "446": "1",
        "447": "1",
        "448": "1",
        "449": "1",
        "45": "1",
        "450": "1",
        "451": "1",
        "452": "1",
        "453": "1",
        "454": "1",
        "46": "1",
        "47": "1",
        "48": "1",
        "49": "1",
        "5": "1",
        "50": "1",
        "51": "1",
        "52": "1",
        "53": "1",
        "54": "1",
        "55": "1",
        "56": "1",
        "57": "1",
        "58": "1",
        "59": "1",
        "6": "1",
        "60": "1",
        "61": "1",
        "62": "1",
        "63": "1",
        "64": "1",
        "65": "1",
        "66": "1",
        "67": "1",
        "68": "1",
        "69": "1",
        "7": "1",
        "70": "1",
        "71": "1",
        "72": "1",
        "73": "1",
        "74": "1",
        "75": "1",
        "76": "1",
        "77": "1",
        "78": "1",
        "79": "1",
        "8": "1",
        "80": "1",
        "81": "1",
        "82": "1",
        "83": "1",
        "84": "1",
        "85": "1",
        "86": "1",
        "87": "1",
        "88": "1",
        "89": "1",
        "9": "1",
        "90": "1",
        "91": "1",
        "92": "1",
        "93": "1",
        "94": "1",
        "95": "1",
        "96": "1",
        "97": "1",
        "98": "1",
        "99": "1"
    },
    "VISIT_LOCATION_SECTION": {
        "10": "496",
        "100": "1140",
        "101": "1417",
        "102": "1108",
        "103": "1165",
        "104": "1385",
        "105": null,
        "106": "1216",
        "107": "1638",
        "108": "2043",
        "109": "629",
        "11": "240",
        "110": null,
        "111": "748",
        "112": "1552",
        "113": "1545",
        "114": "1809",
        "115": "1454",
        "116": "224",
        "117": "730",
        "118": "36",
        "119": "861",
        "12": "1774",
        "120": "450",
        "121": "524",
        "122": "878",
        "123": "991",
        "124": "665",
        "125": "1741",
        "126": "809",
        "127": "75",
        "128": "739",
        "129": "819",
        "13": "194",
        "130": "1280",
        "131": "646",
        "132": "237",
        "133": null,
        "134": "2095",
        "135": "1793",
        "136": "550",
        "137": "1565",
        "138": "1785",
        "139": null,
        "14": "1045",
        "140": "2096",
        "141": "690",
        "142": "1702",
        "143": "898",
        "144": "1583",
        "145": "1244",
        "146": "1428",
        "147": "1748",
        "148": "676",
        "149": "17",
        "15": null,
        "150": "1086",
        "151": "393",
        "152": "383",
        "153": "754",
        "154": "2145",
        "155": "218",
        "156": "1339",
        "157": "1476",
        "158": "843",
        "159": "801",
        "16": "1132",
        "160": "1792",
        "161": "1682",
        "162": "1990",
        "163": null,
        "164": "69",
        "165": "1888",
        "166": null,
        "167": "1188",
        "168": null,
        "169": "1608",
        "17": "1830",
        "170": "1157",
        "171": "1319",
        "172": "328",
        "173": "1452",
        "174": "528",
        "175": "219",
        "176": "602",
        "177": "552",
        "178": "1189",
        "179": "848",
        "18": "1237",
        "180": "1081",
        "181": "9",
        "182": "1025",
        "183": "985",
        "184": "668",
        "185": null,
        "186": "659",
        "187": "612",
        "188": "911",
        "189": "1931",
        "19": null,
        "190": "478",
        "191": null,
        "192": "490",
        "193": "829",
        "194": "859",
        "195": "2070",
        "196": "620",
        "197": "68",
        "198": "1683",
        "199": null,
        "2": "1137",
        "20": "1263",
        "200": "1329",
        "201": "2011",
        "202": "31",
        "203": "1209",
        "204": "833",
        "205": "599",
        "206": null,
        "207": "1904",
        "208": "845",
        "209": "929",
        "21": null,
        "210": "397",
        "211": "624",
        "212": "1790",
        "213": "514",
        "214": "1266",
        "215": "1142",
        "216": "473",
        "217": "73",
        "218": "6",
        "219": "1880",
        "22": "1876",
        "220": "866",
        "221": "1594",
        "222": "1350",
        "223": "717",
        "224": "48",
        "225": "1235",
        "226": "320",
        "227": "407",
        "228": "1573",
        "229": "149",
        "23": "1052",
        "230": "1359",
        "231": "681",
        "232": "1560",
        "233": "304",
        "234": null,
        "235": "1312",
        "236": "876",
        "237": "42",
        "238": "667",
        "239": "2002",
        "24": "675",
        "240": "1139",
        "241": "1258",
        "242": "1397",
        "243": null,
        "244": null,
        "245": "448",
        "246": "2089",
        "247": "1238",
        "248": "1807",
        "249": "334",
        "25": "346",
        "250": "762",
        "251": "1326",
        "252": "1389",
        "253": "1271",
        "254": "117",
        "255": null,
        "256": "770",
        "257": "1661",
        "258": null,
        "259": "1345",
        "26": "744",
        "260": "337",
        "261": "1580",
        "262": "124",
        "263": "30",
        "264": "1606",
        "265": "1688",
        "266": null,
        "267": "1423",
        "268": "838",
        "269": "71",
        "27": "171",
        "270": "1472",
        "271": "782",
        "272": "662",
        "273": "1510",
        "274": "606",
        "275": "440",
        "276": "756",
        "277": "554",
        "278": "1917",
        "279": "84",
        "28": "392",
        "280": "1002",
        "281": "257",
        "282": "1710",
        "283": "1882",
        "284": "1561",
        "285": "1281",
        "286": "227",
        "287": "1865",
        "288": "1420",
        "289": "813",
        "29": "470",
        "290": null,
        "291": "691",
        "292": null,
        "293": "746",
        "294": "2075",
        "295": "2015",
        "296": "13",
        "297": "1506",
        "298": "301",
        "299": "403",
        "3": null,
        "30": "1817",
        "300": "2102",
        "301": null,
        "302": "2059",
        "303": "1102",
        "304": "952",
        "305": "43",
        "306": "1731",
        "307": null,
        "308": "1446",
        "309": null,
        "31": "469",
        "310": "1856",
        "311": "1151",
        "312": "537",
        "313": "1923",
        "314": "572",
        "315": "468",
        "316": "745",
        "317": "1207",
        "318": "1659",
        "319": "954",
        "32": "1129",
        "320": "562",
        "321": "365",
        "322": "1776",
        "323": "510",
        "324": "100",
        "325": "706",
        "326": "1071",
        "327": "1488",
        "328": "1119",
        "329": "956",
        "33": "1034",
        "330": "1455",
        "331": "1289",
        "332": "1076",
        "333": "1406",
        "334": "582",
        "335": "281",
        "336": null,
        "337": "538",
        "338": "1415",
        "339": "907",
        "34": "1172",
        "340": "1094",
        "341": "1590",
        "342": "1903",
        "343": "1083",
        "344": "93",
        "345": "727",
        "346": null,
        "347": null,
        "348": "2141",
        "349": "998",
        "35": "1844",
        "350": "1999",
        "351": "631",
        "352": "1811",
        "353": "228",
        "354": null,
        "355": "150",
        "356": "1907",
        "357": "1374",
        "358": "255",
        "359": "1521",
        "36": null,
        "360": "499",
        "361": "1625",
        "362": "639",
        "363": "27",
        "364": null,
        "365": "1558",
        "366": "1771",
        "367": "1459",
        "368": "1896",
        "369": "2040",
        "37": "1134",
        "370": "193",
        "371": "2000",
        "372": "454",
        "373": "992",
        "374": "1323",
        "375": "1012",
        "376": "1201",
        "377": "1604",
        "378": "1315",
        "379": null,
        "38": "151",
        "380": null,
        "381": "1193",
        "382": "1169",
        "383": "1852",
        "384": "239",
        "385": "2061",
        "386": "1053",
        "387": "169",
        "388": "354",
        "389": "1885",
        "39": "336",
        "390": "989",
        "391": "96",
        "392": "1184",
        "393": "1118",
        "394": "669",
        "395": "1994",
        "396": "2163",
        "397": "2090",
        "398": "1229",
        "399": null,
        "4": "1416",
        "40": "21",
        "400": "23",
        "401": "2116",
        "402": "1257",
        "403": "1612",
        "404": "1429",
        "405": "950",
        "406": "1922",
        "407": "553",
        "408": "49",
        "409": "318",
        "41": "1485",
        "410": "822",
        "411": "1513",
        "412": "927",
        "413": "1863",
        "414": null,
        "415": "1708",
        "416": "174",
        "417": "1887",
        "418": "1072",
        "419": "120",
        "42": "313",
        "420": "738",
        "421": "1854",
        "422": "947",
        "423": "292",
        "424": "329",
        "425": "197",
        "426": "51",
        "427": "160",
        "428": "932",
        "429": "267",
        "43": "1331",
        "430": "1642",
        "431": "1557",
        "432": "1432",
        "433": null,
        "434": "1062",
        "435": "1853",
        "436": "1762",
        "437": "600",
        "438": "1282",
        "439": "1828",
        "44": "1107",
        "440": "1156",
        "441": "67",
        "442": "1458",
        "443": "585",
        "444": "1966",
        "445": "2130",
        "446": "656",
        "447": "129",
        "448": null,
        "449": "887",
        "45": "2008",
        "450": "1837",
        "451": "1746",
        "452": "661",
        "453": "1158",
        "454": "1005",
        "455": "1819",
        "456": "1523",
        "457": "1576",
        "458": "1925",
        "459": "1431",
        "46": "561",
        "460": "137",
        "461": "869",
        "462": "196",
        "463": "1855",
        "464": "107",
        "465": "1355",
        "466": "965",
        "467": "685",
        "468": "1351",
        "469": "1881",
        "47": "1693",
        "470": "682",
        "471": "158",
        "472": "970",
        "473": "1584",
        "474": null,
        "475": "802",
        "476": "125",
        "477": "52",
        "478": "1161",
        "479": "81",
        "48": "1732",
        "480": "693",
        "481": "1054",
        "482": "2085",
        "483": null,
        "484": "733",
        "485": "1712",
        "486": "1984",
        "487": "2032",
        "488": "315",
        "489": "325",
        "49": "1457",
        "490": "2009",
        "491": "657",
        "492": "1464",
        "493": "1386",
        "494": "2076",
        "495": "1049",
        "496": "1318",
        "497": "1569",
        "498": "1981",
        "499": "420",
        "5": "278",
        "50": "1666",
        "500": null,
        "501": "319",
        "502": "1310",
        "503": "697",
        "504": "786",
        "505": "438",
        "506": "955",
        "507": "2012",
        "508": "2111",
        "509": "16",
        "51": null,
        "510": "488",
        "511": null,
        "512": "1820",
        "513": "266",
        "514": "442",
        "515": "767",
        "516": "1756",
        "517": "1849",
        "518": "121",
        "519": "2160",
        "52": "1269",
        "520": "721",
        "521": "977",
        "522": "1918",
        "523": "1537",
        "524": "607",
        "525": "2082",
        "526": "852",
        "527": "1410",
        "528": null,
        "529": "708",
        "53": "423",
        "530": "1655",
        "531": "627",
        "532": null,
        "533": null,
        "534": "1451",
        "535": "573",
        "536": "560",
        "537": "1993",
        "538": "236",
        "539": "1208",
        "54": null,
        "540": "595",
        "541": "29",
        "542": "1892",
        "543": "139",
        "544": "915",
        "545": "2105",
        "546": "785",
        "547": "1525",
        "548": "1621",
        "549": "1482",
        "55": "1734",
        "550": "299",
        "551": "904",
        "552": null,
        "553": null,
        "554": "1791",
        "555": "1635",
        "556": "1372",
        "557": "489",
        "558": "191",
        "559": "138",
        "56": "1210",
        "560": "1579",
        "561": "1327",
        "562": "1075",
        "563": "2121",
        "564": "1297",
        "565": null,
        "566": "245",
        "567": "1341",
        "568": null,
        "569": "967",
        "57": "1816",
        "570": "1941",
        "571": "652",
        "572": "1106",
        "573": "1407",
        "574": "200",
        "575": "1274",
        "576": "1707",
        "577": "1009",
        "578": "47",
        "579": null,
        "58": "677",
        "580": "1085",
        "581": "1519",
        "582": "2083",
        "583": "509",
        "584": "634",
        "585": "1663",
        "586": "1935",
        "587": "1921",
        "588": "774",
        "589": "1900",
        "59": "815",
        "590": null,
        "591": "814",
        "592": "1148",
        "593": "2119",
        "594": "1494",
        "595": "1910",
        "596": "24",
        "597": "868",
        "598": "1205",
        "599": "851",
        "6": "2071",
        "60": "512",
        "600": "787",
        "601": "778",
        "602": "1020",
        "603": "288",
        "604": null,
        "605": "1804",
        "606": "2092",
        "607": "211",
        "608": "360",
        "609": "855",
        "61": null,
        "610": "250",
        "611": "1978",
        "612": "604",
        "613": "692",
        "614": "1400",
        "615": "502",
        "616": null,
        "617": "1928",
        "618": "1603",
        "619": "1701",
        "62": "1685",
        "620": null,
        "621": null,
        "622": "710",
        "623": null,
        "624": "1398",
        "625": null,
        "626": "611",
        "627": "705",
        "628": "205",
        "629": "581",
        "63": "234",
        "630": "265",
        "631": "798",
        "632": null,
        "633": null,
        "634": "805",
        "635": "105",
        "636": "2053",
        "637": "1980",
        "638": "1383",
        "639": "995",
        "64": "22",
        "640": "1231",
        "641": "465",
        "642": null,
        "643": "542",
        "644": "175",
        "645": "369",
        "646": "578",
        "647": "921",
        "648": "2069",
        "649": "804",
        "65": "187",
        "650": "1426",
        "651": "1768",
        "652": "1481",
        "653": null,
        "654": "1273",
        "655": null,
        "656": "2017",
        "657": "603",
        "658": "1056",
        "659": "1577",
        "66": "260",
        "660": "2081",
        "661": "404",
        "662": "165",
        "663": "1528",
        "664": "1252",
        "665": "709",
        "666": "1384",
        "667": null,
        "668": "1078",
        "669": "300",
        "67": "1862",
        "670": "732",
        "671": "565",
        "672": "1037",
        "673": "1765",
        "674": "1241",
        "675": "1320",
        "676": "642",
        "677": "1041",
        "678": "990",
        "679": "1362",
        "68": "1736",
        "680": "1985",
        "681": null,
        "682": "974",
        "683": "7",
        "69": "477",
        "7": null,
        "70": "765",
        "71": "2169",
        "72": "830",
        "73": "1495",
        "74": "58",
        "75": "487",
        "76": "1306",
        "77": "1704",
        "78": null,
        "79": "1111",
        "8": null,
        "80": "1662",
        "81": "484",
        "82": "432",
        "83": "1857",
        "84": "1992",
        "85": "1259",
        "86": "948",
        "87": "435",
        "88": "1404",
        "89": "1324",
        "9": "1325",
        "90": "1163",
        "91": "153",
        "92": "1124",
        "93": "428",
        "94": "1500",
        "95": "1001",
        "96": "1543",
        "97": "791",
        "98": "547",
        "99": "1596"
    }
}